lif_neuron.v
// =============================================================================
// Module  : lif_neuron (v2 - STDP 연동 버전)
// Project : Neuromorphic Chip
//
// [변경 사항 from v1]
//   - WEIGHT 파라미터 제거
//   - spike_in 제거
//   - input_current [7:0] 추가: 시냅스가 계산한 전류를 직접 입력받음
//     (시냅스가 "spike × weight" 계산 후 전달)
//
// Description:
//   매 클럭마다:
//     1. LEAK만큼 막전위 감소 (Underflow 방지)
//     2. input_current를 막전위에 더함 (Overflow 포화 처리)
//     3. THRESHOLD 초과 시 spike_out=1, 다음 클럭에 v_mem=0 리셋
// =============================================================================

module lif_neuron #(
    parameter [7:0] THRESHOLD = 8'd127,  // 발화 임계값
    parameter [7:0] LEAK      = 8'd5     // 클럭당 누설 전류
)(
    input  wire       clk,
    input  wire       rst_n,
    input  wire [7:0] input_current,     // 시냅스로부터 받는 입력 전류

    output reg        spike_out,         // 발화 출력
    output wire [7:0] v_mem              // 막전위 모니터링
);

    // -------------------------------------------------------------------------
    // 내부 레지스터
    // -------------------------------------------------------------------------
    reg [7:0] v_mem_reg;

    // -------------------------------------------------------------------------
    // 조합 논리: Leak 감소 (9-bit 언더플로우 감지)
    // -------------------------------------------------------------------------
    wire [8:0] v_after_leak   = {1'b0, v_mem_reg} - {1'b0, LEAK};
    wire [7:0] v_leak_clamped = v_after_leak[8] ? 8'd0 : v_after_leak[7:0];

    // -------------------------------------------------------------------------
    // 조합 논리: 입력 전류 적분 (9-bit 오버플로우 감지 → 255 포화)
    // -------------------------------------------------------------------------
    wire [8:0] v_after_current = {1'b0, v_leak_clamped} + {1'b0, input_current};
    wire [7:0] v_integrated    = v_after_current[8] ? 8'd255 : v_after_current[7:0];

    // -------------------------------------------------------------------------
    // 순차 논리: 막전위 업데이트
    // -------------------------------------------------------------------------
    always @(posedge clk or negedge rst_n) begin
        if (!rst_n) begin
            v_mem_reg <= 8'd0;
            spike_out <= 1'b0;
        end
        else begin
            if (spike_out) begin
                // 발화 직후: 절대 불응기 → 막전위 리셋
                v_mem_reg <= 8'd0;
                spike_out <= 1'b0;
            end
            else begin
                if (v_integrated > THRESHOLD) begin
                    // 임계값 초과 → 발화
                    v_mem_reg <= v_integrated;
                    spike_out <= 1'b1;
                end
                else begin
                    v_mem_reg <= v_integrated;
                    spike_out <= 1'b0;
                end
            end
        end
    end

    // -------------------------------------------------------------------------
    // 출력
    // -------------------------------------------------------------------------
    assign v_mem = v_mem_reg;

endmodule
// =============================================================================
// End of lif_neuron.v (v2)
// =============================================================================

synapse.v
// =============================================================================
// Module  : synapse
// Project : Neuromorphic Chip - STDP Learning Synapse
// 
// Description:
//   STDP(Spike-Timing Dependent Plasticity) 학습 규칙을 구현한 시냅스 모듈.
//   pre_spike와 post_spike의 순서를 비교하여 가중치(weight)를 자동 조절.
//
//   LTP (Long-Term Potentiation / 강화):
//     pre_spike → post_spike 순서 (인과관계 성립)
//     → weight = weight + LTP_STEP (최대 MAX_WEIGHT 클램핑)
//
//   LTD (Long-Term Depression / 약화):
//     post_spike → pre_spike 순서 (인과관계 불성립)
//     → weight = weight - LTD_STEP (최소 MIN_WEIGHT 클램핑)
//
// Parameters:
//   INIT_WEIGHT : 초기 가중치 (default 10)
//   MAX_WEIGHT  : 가중치 상한 (default 255)
//   MIN_WEIGHT  : 가중치 하한 (default 0)
//   LTP_STEP    : LTP 강화 스텝 (default 1)
//   LTD_STEP    : LTD 약화 스텝 (default 1)
//   TRACE_DECAY : 트레이스 유지 윈도우 (클럭 수, default 8)
//                 이 클럭 수 이내에 반대 스파이크가 오면 STDP 적용
//
// I/O:
//   clk             : 시스템 클럭
//   rst_n           : 비동기 액티브 로우 리셋
//   pre_spike       : 시냅스 전 뉴런(Pre-synaptic) 스파이크
//   post_spike      : 시냅스 후 뉴런(Post-synaptic) 스파이크
//   weighted_current: 출력 전류 = pre_spike가 1일 때 weight 값 전달
//   weight          : 현재 가중치 (모니터링용)
// =============================================================================

module synapse #(
    parameter [7:0] INIT_WEIGHT  = 8'd10,  // 초기 가중치
    parameter [7:0] MAX_WEIGHT   = 8'd255, // 가중치 상한
    parameter [7:0] MIN_WEIGHT   = 8'd0,   // 가중치 하한
    parameter [7:0] LTP_STEP     = 8'd1,   // LTP 강화 스텝
    parameter [7:0] LTD_STEP     = 8'd1,   // LTD 약화 스텝
    parameter [3:0] TRACE_DECAY  = 4'd8    // 스파이크 트레이스 유지 윈도우 (클럭)
)(
    input  wire       clk,
    input  wire       rst_n,
    input  wire       pre_spike,        // Pre-synaptic 뉴런 스파이크
    input  wire       post_spike,       // Post-synaptic 뉴런 스파이크

    output wire [7:0] weighted_current, // Post 뉴런으로 전달할 전류
    output wire [7:0] weight            // 현재 가중치 (모니터링)
);

    // -------------------------------------------------------------------------
    // 내부 레지스터
    // -------------------------------------------------------------------------
    reg [7:0] weight_reg;       // 가중치 레지스터

    // 스파이크 트레이스 카운터
    // pre_trace  : pre_spike 발생 후 몇 클럭이 지났는지 카운트
    // post_trace : post_spike 발생 후 몇 클럭이 지났는지 카운트
    // 값이 0이면 "최근에 스파이크 없음", 양수면 "최근 스파이크 있음"
    reg [3:0] pre_trace;        // Pre-spike 트레이스 카운터
    reg [3:0] post_trace;       // Post-spike 트레이스 카운터

    // -------------------------------------------------------------------------
    // 가중치 업데이트 조합 논리
    // 9-bit 연산으로 오버플로우/언더플로우 감지 후 클램핑
    // -------------------------------------------------------------------------
    wire [8:0] weight_ltp = {1'b0, weight_reg} + {1'b0, LTP_STEP};
    wire [8:0] weight_ltd = {1'b0, weight_reg} - {1'b0, LTD_STEP};

    // LTP 적용 후 클램핑 (MAX_WEIGHT 초과 방지)
    wire [7:0] weight_after_ltp =
        (weight_ltp > {1'b0, MAX_WEIGHT}) ? MAX_WEIGHT : weight_ltp[7:0];

    // LTD 적용 후 클램핑 (MIN_WEIGHT 미만 방지, 언더플로우 감지)
    wire [7:0] weight_after_ltd =
        (weight_ltd[8]) ? MIN_WEIGHT :                          // 언더플로우
        (weight_ltd[7:0] < MIN_WEIGHT) ? MIN_WEIGHT :           // 최솟값 미만
        weight_ltd[7:0];

    // -------------------------------------------------------------------------
    // 순차 논리: 트레이스 업데이트 + STDP 가중치 조절
    // -------------------------------------------------------------------------
    always @(posedge clk or negedge rst_n) begin
        if (!rst_n) begin
            weight_reg <= INIT_WEIGHT;
            pre_trace  <= 4'd0;
            post_trace <= 4'd0;
        end
        else begin
            // -----------------------------------------------------------------
            // 트레이스 카운터 업데이트
            //   스파이크 발생 시 → 카운터를 TRACE_DECAY로 리셋 (최대값 설정)
            //   스파이크 없을 시 → 카운터를 1씩 감소 (0에서 멈춤)
            // -----------------------------------------------------------------
            if (pre_spike)
                pre_trace <= TRACE_DECAY;
            else if (pre_trace > 4'd0)
                pre_trace <= pre_trace - 4'd1;

            if (post_spike)
                post_trace <= TRACE_DECAY;
            else if (post_trace > 4'd0)
                post_trace <= post_trace - 4'd1;

            // -----------------------------------------------------------------
            // STDP 가중치 업데이트
            //
            // LTP: post_spike가 발생했을 때 pre_trace가 살아있으면
            //      → pre가 먼저 왔고 post가 나중에 왔다 = 인과관계 성립
            //      → 가중치 강화
            //
            // LTD: pre_spike가 발생했을 때 post_trace가 살아있으면
            //      → post가 먼저 왔고 pre가 나중에 왔다 = 인과관계 불성립
            //      → 가중치 약화
            //
            // 우선순위: LTP > LTD (동시 발생 시 LTP 우선)
            // -----------------------------------------------------------------
            if (post_spike && (pre_trace > 4'd0)) begin
                // LTP: pre → post 순서 확인됨 → 강화
                weight_reg <= weight_after_ltp;
            end
            else if (pre_spike && (post_trace > 4'd0)) begin
                // LTD: post → pre 순서 확인됨 → 약화
                weight_reg <= weight_after_ltd;
            end
            // 그 외: 가중치 유지
        end
    end

    // -------------------------------------------------------------------------
    // 출력 할당
    //   weighted_current: pre_spike가 1일 때만 weight를 전달
    //                     (스파이크가 없으면 전류 0)
    // -------------------------------------------------------------------------
    assign weighted_current = pre_spike ? weight_reg : 8'd0;
    assign weight           = weight_reg;

endmodule
// =============================================================================
// End of synapse.v
// =============================================================================

network.v
// =============================================================================
// Module  : network (v2 - STDP 학습 시냅스 연동)
// Project : Neuromorphic Chip
//
// 구조:
//   spike_in_global
//        │  input_current_n1 (고정값)
//        ▼
//   [N1: lif_neuron]
//        │ pre_spike (spike_out_n1)
//        ▼
//   [Synapse: STDP]  ←── post_spike (spike_out_n2) 피드백
//        │ weighted_current
//        ▼
//   [N2: lif_neuron]
//        │ spike_out_n2 (최종 출력)
//
// 핵심:
//   - N1이 발화 → Synapse가 weighted_current를 N2에 전달
//   - N2가 발화 → Synapse에 post_spike로 피드백
//   - Synapse는 pre/post 타이밍 비교 → weight 자동 조절 (STDP)
// =============================================================================

module network #(
    // N1 파라미터
    parameter [7:0] N1_THRESHOLD     = 8'd60,
    parameter [7:0] N1_LEAK          = 8'd5,
    parameter [7:0] N1_INPUT_CURRENT = 8'd20,  // N1에 고정으로 들어오는 전류

    // N2 파라미터
    parameter [7:0] N2_THRESHOLD     = 8'd60,
    parameter [7:0] N2_LEAK          = 8'd5,

    // Synapse STDP 파라미터
    parameter [7:0] SYN_INIT_WEIGHT  = 8'd10,
    parameter [7:0] SYN_MAX_WEIGHT   = 8'd255,
    parameter [7:0] SYN_MIN_WEIGHT   = 8'd0,
    parameter [7:0] SYN_LTP_STEP     = 8'd1,
    parameter [7:0] SYN_LTD_STEP     = 8'd1,
    parameter [3:0] SYN_TRACE_DECAY  = 4'd8
)(
    input  wire       clk,
    input  wire       rst_n,
    input  wire       spike_in_global,  // 외부 자극 (N1 활성화용)

    output wire       spike_out_n1,     // N1 발화 출력
    output wire       spike_out_n2,     // N2 발화 출력 (최종)
    output wire [7:0] v_mem_n1,         // N1 막전위 (모니터링)
    output wire [7:0] v_mem_n2,         // N2 막전위 (모니터링)
    output wire [7:0] syn_weight        // 시냅스 가중치 (학습 관찰용)
);

    // -------------------------------------------------------------------------
    // 내부 연결 와이어
    // -------------------------------------------------------------------------
    wire [7:0] n1_input_current;    // N1으로 들어가는 전류
    wire [7:0] syn_current_to_n2;   // Synapse → N2 전류

    // N1 입력 전류: spike_in_global이 1일 때만 N1_INPUT_CURRENT 전달
    assign n1_input_current = spike_in_global ? N1_INPUT_CURRENT : 8'd0;

    // -------------------------------------------------------------------------
    // N1: 감각 뉴런 (Pre-synaptic Neuron)
    // -------------------------------------------------------------------------
    lif_neuron #(
        .THRESHOLD(N1_THRESHOLD),
        .LEAK     (N1_LEAK)
    ) neuron1 (
        .clk          (clk),
        .rst_n        (rst_n),
        .input_current(n1_input_current),
        .spike_out    (spike_out_n1),
        .v_mem        (v_mem_n1)
    );

    // -------------------------------------------------------------------------
    // Synapse: STDP 학습 시냅스
    //   - pre_spike  = N1의 발화 출력
    //   - post_spike = N2의 발화 출력 (피드백 연결)
    // -------------------------------------------------------------------------
    synapse #(
        .INIT_WEIGHT (SYN_INIT_WEIGHT),
        .MAX_WEIGHT  (SYN_MAX_WEIGHT),
        .MIN_WEIGHT  (SYN_MIN_WEIGHT),
        .LTP_STEP    (SYN_LTP_STEP),
        .LTD_STEP    (SYN_LTD_STEP),
        .TRACE_DECAY (SYN_TRACE_DECAY)
    ) syn (
        .clk             (clk),
        .rst_n           (rst_n),
        .pre_spike       (spike_out_n1),   // N1 발화 → 시냅스 입력
        .post_spike      (spike_out_n2),   // N2 발화 → 피드백
        .weighted_current(syn_current_to_n2),
        .weight          (syn_weight)
    );

    // -------------------------------------------------------------------------
    // N2: 운동 뉴런 (Post-synaptic Neuron)
    // -------------------------------------------------------------------------
    lif_neuron #(
        .THRESHOLD(N2_THRESHOLD),
        .LEAK     (N2_LEAK)
    ) neuron2 (
        .clk          (clk),
        .rst_n        (rst_n),
        .input_current(syn_current_to_n2), // 시냅스 출력 전류 수신
        .spike_out    (spike_out_n2),
        .v_mem        (v_mem_n2)
    );

endmodule
// =============================================================================
// End of network.v (v2)
// =============================================================================

tb_network.v
// =============================================================================
// Module  : tb_network (v3 - STDP 학습 버그 수정)
//
// [버그 수정]
//   기존 파라미터 문제:
//     N1 발화 주기 = 5클럭, 그 사이 N2 Leak = -5 × 5 = -25
//     N1 발화 시 N2에 전달되는 전류 = weight(10) → 누적 불가능
//     → N2가 절대 발화 못함 → post_spike=0 → LTP 조건 불성립 → weight 고정
//
//   해결책:
//     N2_LEAK=1로 줄여 전압 유지 시간 연장
//     SYN_INIT_WEIGHT=30으로 올려 N2가 초반에 발화 가능하게
//     → N2 발화 후 LTP 적용 → weight 증가 → 더 빠른 발화 확인
//
// 관전 포인트:
//   Syn_W가 30 → 32 → 34 ... 증가하면 STDP LTP 학습 성공!
//   N2 발화 주기가 점점 짧아지면 완벽!
// =============================================================================
`timescale 1ns / 1ps

module tb_network;

    // -------------------------------------------------------------------------
    // 신호 선언
    // -------------------------------------------------------------------------
    reg        clk;
    reg        rst_n;
    reg        spike_in;

    wire       spike_out_n1;
    wire       spike_out_n2;
    wire [7:0] v1, v2;
    wire [7:0] syn_weight;

    // -------------------------------------------------------------------------
    // DUT 연결 (파라미터 재설계)
    //
    // N1: THRESHOLD=60, LEAK=5, INPUT_CURRENT=20
    //     → 순증가 +15/cycle → 4클럭마다 발화
    //
    // Synapse: INIT_WEIGHT=30
    //     → N1 발화 시 N2에 30 전달
    //
    // N2: THRESHOLD=60, LEAK=1
    //     → N1 발화 사이 4클럭 동안 Leak = -1×4 = -4 (매우 적음)
    //     → 30 → 26 → 22 → 18 → 14 (다음 N1 발화) → 44 → ...
    //     → 2번째 N1 발화 후: 44 → 40 → 36 → 32 → 28 (다음) → 58
    //     → 3번째 N1 발화 후: 58 → 54 → 50 → 46 → 42 (다음) → 72 > 60 → 발화!
    // -------------------------------------------------------------------------
    network #(
        .N1_THRESHOLD    (8'd60),
        .N1_LEAK         (8'd5),
        .N1_INPUT_CURRENT(8'd20),
        .N2_THRESHOLD    (8'd60),
        .N2_LEAK         (8'd1),   // ← 핵심 수정: Leak 줄여서 N2 전압 유지
        .SYN_INIT_WEIGHT (8'd30),  // ← 핵심 수정: 초기 weight 높여서 N2 발화 유도
        .SYN_LTP_STEP    (8'd2),   // LTP 스텝 2 (학습 효과 빠르게 관찰)
        .SYN_LTD_STEP    (8'd1),
        .SYN_TRACE_DECAY (4'd8)
    ) uut (
        .clk            (clk),
        .rst_n          (rst_n),
        .spike_in_global(spike_in),
        .spike_out_n1   (spike_out_n1),
        .spike_out_n2   (spike_out_n2),
        .v_mem_n1       (v1),
        .v_mem_n2       (v2),
        .syn_weight     (syn_weight)
    );

    // -------------------------------------------------------------------------
    // 클럭 생성 (10ns = 100MHz)
    // -------------------------------------------------------------------------
    initial clk = 0;
    always  #5 clk = ~clk;

    // -------------------------------------------------------------------------
    // 태스크
    // -------------------------------------------------------------------------
    task set_spike;
        input val;
        begin
            @(posedge clk); #1;
            spike_in = val;
        end
    endtask

    integer i;

    initial begin
        $dumpfile("network_dump.vcd");
        $dumpvars(0, tb_network);

        rst_n    = 0;
        spike_in = 0;
        @(posedge clk); #1;
        @(posedge clk); #1;
        rst_n = 1;

        // =================================================================
        // [시나리오 1] 연속 자극 150회
        //   초반: weight=30 → N2가 3~4번 N1 발화 후 첫 발화
        //   LTP 적용 후: weight 증가 → N2 발화 주기 단축 확인
        // =================================================================
        $display("\n[시나리오 1] 연속 자극 150회 - STDP LTP 학습 관찰");
        $display("  Syn_W가 30에서 증가하면 학습 성공!");
        for (i = 0; i < 150; i = i + 1) begin
            set_spike(1);
        end

        // =================================================================
        // [시나리오 2] 입력 중단 - Leak 관찰 (weight는 유지됨)
        // =================================================================
        $display("\n[시나리오 2] 입력 중단 - weight 유지 확인");
        for (i = 0; i < 20; i = i + 1) begin
            set_spike(0);
        end

        // =================================================================
        // [시나리오 3] 재자극 - 학습된 weight로 N2 더 빨리 발화하는지 확인
        // =================================================================
        $display("\n[시나리오 3] 재자극 - 높아진 weight 효과 확인");
        for (i = 0; i < 80; i = i + 1) begin
            set_spike(1);
        end

        $display("\n[시뮬레이션 완료]");
        $finish;
    end

    // -------------------------------------------------------------------------
    // 모니터링
    // -------------------------------------------------------------------------
    initial begin
        $monitor("T=%t | In=%b | N1_V=%3d(F:%b) | Syn_W=%3d | N2_V=%3d(F:%b)",
                 $time, spike_in,
                 v1, spike_out_n1,
                 syn_weight,
                 v2, spike_out_n2);
    end

endmodule
// =============================================================================
// End of tb_network.v (v3)
// =============================================================================

network_dump.vcd
$date
	Wed Feb 18 09:07:31 2026
$end
$version
	Icarus Verilog
$end
$timescale
	1ps
$end
$scope module tb_network $end
$var wire 8 ! v2 [7:0] $end
$var wire 8 " v1 [7:0] $end
$var wire 8 # syn_weight [7:0] $end
$var wire 1 $ spike_out_n2 $end
$var wire 1 % spike_out_n1 $end
$var reg 1 & clk $end
$var reg 1 ' rst_n $end
$var reg 1 ( spike_in $end
$var integer 32 ) i [31:0] $end
$scope module uut $end
$var wire 1 & clk $end
$var wire 1 ' rst_n $end
$var wire 1 ( spike_in_global $end
$var wire 8 * v_mem_n2 [7:0] $end
$var wire 8 + v_mem_n1 [7:0] $end
$var wire 8 , syn_weight [7:0] $end
$var wire 8 - syn_current_to_n2 [7:0] $end
$var wire 1 $ spike_out_n2 $end
$var wire 1 % spike_out_n1 $end
$var wire 8 . n1_input_current [7:0] $end
$scope module neuron1 $end
$var wire 1 & clk $end
$var wire 8 / input_current [7:0] $end
$var wire 1 ' rst_n $end
$var wire 8 0 v_mem [7:0] $end
$var wire 8 1 v_leak_clamped [7:0] $end
$var wire 8 2 v_integrated [7:0] $end
$var wire 9 3 v_after_leak [8:0] $end
$var wire 9 4 v_after_current [8:0] $end
$var reg 1 % spike_out $end
$var reg 8 5 v_mem_reg [7:0] $end
$upscope $end
$scope module neuron2 $end
$var wire 1 & clk $end
$var wire 1 ' rst_n $end
$var wire 8 6 v_mem [7:0] $end
$var wire 8 7 v_leak_clamped [7:0] $end
$var wire 8 8 v_integrated [7:0] $end
$var wire 9 9 v_after_leak [8:0] $end
$var wire 9 : v_after_current [8:0] $end
$var wire 8 ; input_current [7:0] $end
$var reg 1 $ spike_out $end
$var reg 8 < v_mem_reg [7:0] $end
$upscope $end
$scope module syn $end
$var wire 1 & clk $end
$var wire 1 $ post_spike $end
$var wire 1 % pre_spike $end
$var wire 1 ' rst_n $end
$var wire 8 = weight [7:0] $end
$var wire 8 > weighted_current [7:0] $end
$var wire 9 ? weight_ltp [8:0] $end
$var wire 9 @ weight_ltd [8:0] $end
$var wire 8 A weight_after_ltp [7:0] $end
$var wire 8 B weight_after_ltd [7:0] $end
$var reg 4 C post_trace [3:0] $end
$var reg 4 D pre_trace [3:0] $end
$var reg 8 E weight_reg [7:0] $end
$upscope $end
$upscope $end
$scope task set_spike $end
$var reg 1 F val $end
$upscope $end
$upscope $end
$enddefinitions $end
#0
$dumpvars
xF
b11110 E
b0 D
b0 C
b11101 B
b100000 A
b11101 @
b100000 ?
b0 >
b11110 =
b0 <
b0 ;
b0 :
b111111111 9
b0 8
b0 7
b0 6
b0 5
b0 4
b111111011 3
b0 2
b0 1
b0 0
b0 /
b0 .
b0 -
b11110 ,
b0 +
b0 *
bx )
0(
0'
0&
0%
0$
b11110 #
b0 "
b0 !
$end
#5000
1&
#10000
0&
#15000
1&
#16000
1F
b0 )
1'
#20000
0&
#25000
1&
#26000
b10100 2
b10100 4
b10100 .
b10100 /
b1 )
1(
#30000
0&
#35000
b100011 2
b100011 4
b1111 1
b1111 3
b10100 "
b10100 +
b10100 0
b10100 5
1&
#36000
b10 )
#40000
0&
#45000
b110010 2
b110010 4
b11110 1
b11110 3
b100011 "
b100011 +
b100011 0
b100011 5
1&
#46000
b11 )
#50000
0&
#55000
b1000001 2
b1000001 4
b101101 1
b101101 3
b110010 "
b110010 +
b110010 0
b110010 5
1&
#56000
b100 )
#60000
0&
#65000
b1010000 2
b11110 8
b1010000 4
b111100 1
b11110 :
b11110 -
b11110 ;
b11110 >
1%
b111100 3
b1000001 "
b1000001 +
b1000001 0
b1000001 5
1&
#66000
b101 )
#70000
0&
#75000
b10100 2
b11101 8
b10100 4
b0 1
b11101 7
b11101 :
b0 -
b0 ;
b0 >
0%
b111111011 3
b0 "
b0 +
b0 0
b0 5
b1000 D
b11101 9
b11110 !
b11110 *
b11110 6
b11110 <
1&
#76000
b110 )
#80000
0&
#85000
b11100 8
b100011 2
b11100 :
b11100 7
b100011 4
b1111 1
b11100 9
b11101 !
b11101 *
b11101 6
b11101 <
b111 D
b1111 3
b10100 "
b10100 +
b10100 0
b10100 5
1&
#86000
b111 )
#90000
0&
#95000
b110010 2
b11011 8
b110010 4
b11110 1
b11011 :
b11011 7
b11110 3
b100011 "
b100011 +
b100011 0
b100011 5
b110 D
b11011 9
b11100 !
b11100 *
b11100 6
b11100 <
1&
#96000
b1000 )
#100000
0&
#105000
b11010 8
b1000001 2
b11010 :
b11010 7
b1000001 4
b101101 1
b11010 9
b11011 !
b11011 *
b11011 6
b11011 <
b101 D
b101101 3
b110010 "
b110010 +
b110010 0
b110010 5
1&
#106000
b1001 )
#110000
0&
#115000
b1010000 2
b110111 8
b1010000 4
b111100 1
b11001 7
b110111 :
b11110 -
b11110 ;
b11110 >
1%
b111100 3
b1000001 "
b1000001 +
b1000001 0
b1000001 5
b100 D
b11001 9
b11010 !
b11010 *
b11010 6
b11010 <
1&
#116000
b1010 )
#120000
0&
#125000
b10100 2
b110110 8
b110110 7
b10100 4
b0 1
b110110 :
b0 -
b0 ;
b0 >
b110110 9
b110111 !
b110111 *
b110111 6
b110111 <
b1000 D
0%
b111111011 3
b0 "
b0 +
b0 0
b0 5
1&
#126000
b1011 )
#130000
0&
#135000
b100011 2
b110101 8
b100011 4
b1111 1
b110101 :
b110101 7
b1111 3
b10100 "
b10100 +
b10100 0
b10100 5
b111 D
b110101 9
b110110 !
b110110 *
b110110 6
b110110 <
1&
#136000
b1100 )
#140000
0&
#145000
b110100 8
b110010 2
b110100 :
b110100 7
b110010 4
b11110 1
b110100 9
b110101 !
b110101 *
b110101 6
b110101 <
b110 D
b11110 3
b100011 "
b100011 +
b100011 0
b100011 5
1&
#146000
b1101 )
#150000
0&
#155000
b1000001 2
b110011 8
b1000001 4
b101101 1
b110011 :
b110011 7
b101101 3
b110010 "
b110010 +
b110010 0
b110010 5
b101 D
b110011 9
b110100 !
b110100 *
b110100 6
b110100 <
1&
#156000
b1110 )
#160000
0&
#165000
b1010000 2
b1010000 8
b110010 7
b1010000 4
b111100 1
b1010000 :
b11110 -
b11110 ;
b11110 >
b110010 9
b110011 !
b110011 *
b110011 6
b110011 <
b100 D
1%
b111100 3
b1000001 "
b1000001 +
b1000001 0
b1000001 5
1&
#166000
b1111 )
#170000
0&
#175000
b10100 2
b1001111 8
b10100 4
b0 1
b1001111 7
b1001111 :
b0 -
b0 ;
b0 >
0%
b111111011 3
b0 "
b0 +
b0 0
b0 5
b1000 D
1$
b1001111 9
b1010000 !
b1010000 *
b1010000 6
b1010000 <
1&
#176000
b10000 )
#180000
0&
#185000
b0 8
b100011 2
b11111 B
b0 :
b0 7
b100010 A
b100011 4
b1111 1
0$
b111111111 9
b0 !
b0 *
b0 6
b0 <
b100010 ?
b11111 @
b100000 #
b100000 ,
b100000 =
b100000 E
b1000 C
b111 D
b1111 3
b10100 "
b10100 +
b10100 0
b10100 5
1&
#186000
b10001 )
#190000
0&
#195000
b110010 2
b110010 4
b11110 1
b11110 3
b100011 "
b100011 +
b100011 0
b100011 5
b111 C
b110 D
1&
#196000
b10010 )
#200000
0&
#205000
b1000001 2
b1000001 4
b101101 1
b110 C
b101 D
b101101 3
b110010 "
b110010 +
b110010 0
b110010 5
1&
#206000
b10011 )
#210000
0&
#215000
b1010000 2
b100000 8
b1010000 4
b111100 1
b100000 :
b100000 -
b100000 ;
b100000 >
1%
b111100 3
b1000001 "
b1000001 +
b1000001 0
b1000001 5
b101 C
b100 D
1&
#216000
b10100 )
#220000
0&
#225000
b10100 2
b11110 B
b11111 8
b11111 7
b100001 A
b10100 4
b0 1
b11111 :
b0 -
b0 ;
b0 >
b11111 9
b100000 !
b100000 *
b100000 6
b100000 <
b100001 ?
b11110 @
b11111 #
b11111 ,
b11111 =
b11111 E
b100 C
b1000 D
0%
b111111011 3
b0 "
b0 +
b0 0
b0 5
1&
#226000
b10101 )
#230000
0&
#235000
b100011 2
b11110 8
b100011 4
b1111 1
b11110 :
b11110 7
b1111 3
b10100 "
b10100 +
b10100 0
b10100 5
b11 C
b111 D
b11110 9
b11111 !
b11111 *
b11111 6
b11111 <
1&
#236000
b10110 )
#240000
0&
#245000
b11101 8
b110010 2
b11101 :
b11101 7
b110010 4
b11110 1
b11101 9
b11110 !
b11110 *
b11110 6
b11110 <
b10 C
b110 D
b11110 3
b100011 "
b100011 +
b100011 0
b100011 5
1&
#246000
b10111 )
#250000
0&
#255000
b1000001 2
b11100 8
b1000001 4
b101101 1
b11100 :
b11100 7
b101101 3
b110010 "
b110010 +
b110010 0
b110010 5
b1 C
b101 D
b11100 9
b11101 !
b11101 *
b11101 6
b11101 <
1&
#256000
b11000 )
#260000
0&
#265000
b1010000 2
b111010 8
b11011 7
b1010000 4
b111100 1
b111010 :
b11111 -
b11111 ;
b11111 >
b11011 9
b11100 !
b11100 *
b11100 6
b11100 <
b0 C
b100 D
1%
b111100 3
b1000001 "
b1000001 +
b1000001 0
b1000001 5
1&
#266000
b11001 )
#270000
0&
#275000
b10100 2
b111001 8
b10100 4
b0 1
b111001 7
b111001 :
b0 -
b0 ;
b0 >
0%
b111111011 3
b0 "
b0 +
b0 0
b0 5
b1000 D
b111001 9
b111010 !
b111010 *
b111010 6
b111010 <
1&
#276000
b11010 )
#280000
0&
#285000
b111000 8
b100011 2
b111000 :
b111000 7
b100011 4
b1111 1
b111000 9
b111001 !
b111001 *
b111001 6
b111001 <
b111 D
b1111 3
b10100 "
b10100 +
b10100 0
b10100 5
1&
#286000
b11011 )
#290000
0&
#295000
b110010 2
b110111 8
b110010 4
b11110 1
b110111 :
b110111 7
b11110 3
b100011 "
b100011 +
b100011 0
b100011 5
b110 D
b110111 9
b111000 !
b111000 *
b111000 6
b111000 <
1&
#296000
b11100 )
#300000
0&
#305000
b110110 8
b1000001 2
b110110 :
b110110 7
b1000001 4
b101101 1
b110110 9
b110111 !
b110111 *
b110111 6
b110111 <
b101 D
b101101 3
b110010 "
b110010 +
b110010 0
b110010 5
1&
#306000
b11101 )
#310000
0&
#315000
b1010000 2
b1010100 8
b1010000 4
b111100 1
b110101 7
b1010100 :
b11111 -
b11111 ;
b11111 >
1%
b111100 3
b1000001 "
b1000001 +
b1000001 0
b1000001 5
b100 D
b110101 9
b110110 !
b110110 *
b110110 6
b110110 <
1&
#316000
b11110 )
#320000
0&
#325000
b10100 2
b1010011 8
b1010011 7
b10100 4
b0 1
b1010011 :
b0 -
b0 ;
b0 >
1$
b1010011 9
b1010100 !
b1010100 *
b1010100 6
b1010100 <
b1000 D
0%
b111111011 3
b0 "
b0 +
b0 0
b0 5
1&
#326000
b11111 )
#330000
0&
#335000
b100011 2
b0 8
b100000 B
b100011 4
b1111 1
b100011 A
b0 :
b0 7
b1111 3
b10100 "
b10100 +
b10100 0
b10100 5
b100011 ?
b100000 @
b100001 #
b100001 ,
b100001 =
b100001 E
b1000 C
b111 D
0$
b111111111 9
b0 !
b0 *
b0 6
b0 <
1&
#336000
b100000 )
#340000
0&
#345000
b110010 2
b110010 4
b11110 1
b111 C
b110 D
b11110 3
b100011 "
b100011 +
b100011 0
b100011 5
1&
#346000
b100001 )
#350000
0&
#355000
b1000001 2
b1000001 4
b101101 1
b101101 3
b110010 "
b110010 +
b110010 0
b110010 5
b110 C
b101 D
1&
#356000
b100010 )
#360000
0&
#365000
b1010000 2
b100001 8
b1010000 4
b111100 1
b100001 :
b100001 -
b100001 ;
b100001 >
b101 C
b100 D
1%
b111100 3
b1000001 "
b1000001 +
b1000001 0
b1000001 5
1&
#366000
b100011 )
#370000
0&
#375000
b10100 2
b11111 B
b100000 8
b10100 4
b0 1
b100010 A
b100000 7
b100000 :
b0 -
b0 ;
b0 >
0%
b111111011 3
b0 "
b0 +
b0 0
b0 5
b100010 ?
b11111 @
b100000 #
b100000 ,
b100000 =
b100000 E
b100 C
b1000 D
b100000 9
b100001 !
b100001 *
b100001 6
b100001 <
1&
#376000
b100100 )
#380000
0&
#385000
b11111 8
b100011 2
b11111 :
b11111 7
b100011 4
b1111 1
b11111 9
b100000 !
b100000 *
b100000 6
b100000 <
b11 C
b111 D
b1111 3
b10100 "
b10100 +
b10100 0
b10100 5
1&
#386000
b100101 )
#390000
0&
#395000
b110010 2
b11110 8
b110010 4
b11110 1
b11110 :
b11110 7
b11110 3
b100011 "
b100011 +
b100011 0
b100011 5
b10 C
b110 D
b11110 9
b11111 !
b11111 *
b11111 6
b11111 <
1&
#396000
b100110 )
#400000
0&
#405000
b11101 8
b1000001 2
b11101 :
b11101 7
b1000001 4
b101101 1
b11101 9
b11110 !
b11110 *
b11110 6
b11110 <
b1 C
b101 D
b101101 3
b110010 "
b110010 +
b110010 0
b110010 5
1&
#406000
b100111 )
#410000
0&
#415000
b1010000 2
b111100 8
b1010000 4
b111100 1
b11100 7
b111100 :
b100000 -
b100000 ;
b100000 >
1%
b111100 3
b1000001 "
b1000001 +
b1000001 0
b1000001 5
b0 C
b100 D
b11100 9
b11101 !
b11101 *
b11101 6
b11101 <
1&
#416000
b101000 )
#420000
0&
#425000
b10100 2
b111011 8
b111011 7
b10100 4
b0 1
b111011 :
b0 -
b0 ;
b0 >
b111011 9
b111100 !
b111100 *
b111100 6
b111100 <
b1000 D
0%
b111111011 3
b0 "
b0 +
b0 0
b0 5
1&
#426000
b101001 )
#430000
0&
