coincidence_detector.v
// =============================================================================
// Module  : coincidence_detector (v2 - 정확한 circular similarity)
// Project : Phase-based Spiking Transformer (PST)
//
// [v2 수정]
//   GPT 지적 사항 수정:
//   1. wrap-around 계산 정확히 구현
//   2. 9비트 연산으로 언더플로우 방지
//   3. 결과를 같은 사이클에 출력 (combinational)
//
//   [정확한 위상 유사도]
//   Δ = min(|a-b|, 256-|a-b|)   ← 원형 공간 최단 거리
//   Rel = 255 - Δ               ← 유사도 (가까울수록 높음)
//
//   [수학적 성질]
//   - 대칭: Rel(A,B) = Rel(B,A)
//   - 최대: A=B → Δ=0 → Rel=255
//   - 최소: |A-B|=128 → Δ=128 → Rel=127
//   - 단조: 위상 차이 증가 → Rel 감소
//
//   이 성질들이 Transformer QK^T와 동일한 구조
// =============================================================================

module coincidence_detector #(
    parameter [7:0] PHASE_TOL  = 8'd20,
    parameter [7:0] CYCLE_LEN  = 8'd255
)(
    input  wire       clk,
    input  wire       rst_n,
    input  wire       fired_a,
    input  wire       fired_b,
    input  wire [7:0] phase_a,
    input  wire [7:0] phase_b,
    input  wire       cycle_start,

    output reg  [7:0] relevance,
    output reg        coincident
);

    // -------------------------------------------------------------------------
    // 조합 논리: 정확한 circular phase difference
    // -------------------------------------------------------------------------
    // 9비트로 확장하여 언더플로우 방지
    wire [8:0] pa = {1'b0, phase_a};
    wire [8:0] pb = {1'b0, phase_b};

    // |a - b| (절댓값)
    wire [8:0] diff_raw = (pa >= pb) ? (pa - pb) : (pb - pa);

    // circular 최단 거리: min(diff, 256-diff)
    wire [8:0] diff_wrap = 9'd256 - diff_raw;
    wire [7:0] phase_diff = (diff_raw <= diff_wrap) ?
                             diff_raw[7:0] : diff_wrap[7:0];

    // 유사도 = 255 - 최단 거리
    wire [7:0] rel_score = 8'd255 - phase_diff;

    // -------------------------------------------------------------------------
    // 순차 논리: 사이클 시작 시 결과 래치
    // -------------------------------------------------------------------------
    always @(posedge clk or negedge rst_n) begin
        if (!rst_n) begin
            relevance  <= 8'd0;
            coincident <= 1'b0;
        end
        else if (cycle_start) begin
            if (fired_a && fired_b) begin
                relevance  <= rel_score;
                coincident <= (phase_diff <= PHASE_TOL) ? 1'b1 : 1'b0;
            end
            else begin
                relevance  <= 8'd0;
                coincident <= 1'b0;
            end
        end
    end

endmodule
// =============================================================================
// End of coincidence_detector.v (v2)
// =============================================================================

phase_neuron.v
// =============================================================================
// Module  : phase_neuron
// Project : Phase-based Spiking Transformer (PST)
//
// Description:
//   위상 코딩(Phase Coding) 뉴런.
//   입력 전류의 강도를 발화 위상으로 변환.
//
//   [핵심 원리]
//   감마 사이클(0~255) 내에서:
//     강한 입력 → 낮은 위상(초반)에서 발화
//     약한 입력 → 높은 위상(후반)에서 발화
//     입력 없음 → 발화 안 함
//
//   [수식]
//   fire_phase = CYCLE_LEN - (input_current / THRESHOLD × CYCLE_LEN)
//   → input이 THRESHOLD 이상이면 위상 0에서 발화
//   → input이 THRESHOLD/2이면 위상 128에서 발화
//   → input이 0이면 발화 안 함
//
//   [왜 이게 Attention인가]
//   두 뉴런의 발화 위상이 가까울수록 = 두 입력이 비슷한 강도
//   Coincidence Detector가 이를 감지 = 관련성 계산
//   = 행렬 곱셈 없는 Attention!
//
//   [출력]
//   spike_out:  발화 펄스 (1클럭)
//   phase_lock: 발화한 위상값 (다음 사이클까지 유지)
//   fired:      이번 사이클에 발화했는지 여부
// =============================================================================

module phase_neuron #(
    parameter [7:0] THRESHOLD  = 8'd64,   // 발화 최소 입력 강도
    parameter [7:0] LEAK       = 8'd8,    // 사이클 내 누설
    parameter [7:0] CYCLE_LEN  = 8'd255   // 감마 사이클 길이
)(
    input  wire       clk,
    input  wire       rst_n,
    input  wire [7:0] global_phase,    // gamma_oscillator에서 오는 위상
    input  wire       cycle_start,     // 사이클 시작 펄스
    input  wire [7:0] input_current,   // 시냅스 입력 전류

    output reg        spike_out,       // 발화 펄스
    output reg  [7:0] phase_lock,      // 발화한 위상 (유지됨)
    output reg        fired_this_cycle // 이번 사이클 발화 여부
);

    reg [7:0] v_mem;        // 막전위 누적기
    reg       has_fired;    // 이번 사이클 발화 플래그 (중복 발화 방지)
    reg [8:0] v_next;       // 다음 막전위 (9비트 오버플로우 감지용)

    always @(posedge clk or negedge rst_n) begin
        if (!rst_n) begin
            v_mem           <= 8'd0;
            spike_out       <= 1'b0;
            phase_lock      <= 8'd255;  // 발화 안 함 = 최대 위상
            fired_this_cycle<= 1'b0;
            has_fired       <= 1'b0;
            v_next          <= 9'd0;
        end
        else begin
            spike_out <= 1'b0;  // 기본값: 발화 없음

            // ─────────────────────────────────────────────────────
            // 사이클 시작: 막전위 리셋, 발화 플래그 리셋
            // ─────────────────────────────────────────────────────
            if (cycle_start) begin
                v_mem            <= 8'd0;
                has_fired        <= 1'b0;
                fired_this_cycle <= 1'b0;
            end
            else if (!has_fired) begin
                // ─────────────────────────────────────────────────
                // 막전위 누적
                // ─────────────────────────────────────────────────
                v_next = {1'b0, v_mem} + {1'b0, input_current};
                v_mem  <= v_next[8] ? 8'd255 : v_next[7:0];

                // ─────────────────────────────────────────────────
                // 임계값 초과 → 발화 (위상 기록)
                // ─────────────────────────────────────────────────
                if (v_next[8] || v_next[7:0] >= THRESHOLD) begin
                    spike_out        <= 1'b1;
                    phase_lock       <= global_phase;
                    fired_this_cycle <= 1'b1;
                    has_fired        <= 1'b1;
                    v_mem            <= 8'd0;
                end
            end
        end
    end

endmodule
// =============================================================================
// End of phase_neuron.v
// =============================================================================

gamma_oscillator.v
// =============================================================================
// Module  : gamma_oscillator
// Project : Phase-based Spiking Transformer (PST)
//
// Description:
//   뇌의 감마파(Gamma Oscillation, ~40Hz)를 모사하는 전역 위상 생성기.
//   모든 phase_neuron이 이 신호를 공유 → 공통 시간 기준
//
//   [생물학적 대응]
//   해마/피질의 감마 오실레이션
//   → 뉴런들이 이 리듬에 맞춰 발화 위상을 결정
//
//   [동작]
//   CYCLE_LEN 클럭마다 위상 0→CYCLE_LEN-1 반복
//   cycle_start: 사이클 시작 펄스 (1클럭)
//   phase_out:   현재 위상 (0 ~ CYCLE_LEN-1)
//
//   [파라미터]
//   CYCLE_LEN = 256: 위상 해상도 8비트
//                    → 256단계로 입력 강도 표현
// =============================================================================

module gamma_oscillator #(
    parameter [8:0] CYCLE_LEN = 9'd256  // 위상 해상도
)(
    input  wire       clk,
    input  wire       rst_n,
    output reg  [7:0] phase_out,    // 현재 위상 (0~255)
    output reg        cycle_start   // 사이클 시작 펄스
);

    always @(posedge clk or negedge rst_n) begin
        if (!rst_n) begin
            phase_out   <= 8'd0;
            cycle_start <= 1'b0;
        end
        else begin
            if (phase_out == CYCLE_LEN - 1) begin
                phase_out   <= 8'd0;
                cycle_start <= 1'b1;  // 다음 클럭에 새 사이클
            end
            else begin
                phase_out   <= phase_out + 8'd1;
                cycle_start <= 1'b0;
            end
        end
    end

endmodule
// =============================================================================
// End of gamma_oscillator.v
// =============================================================================

tb_phase.v
// =============================================================================
// Module  : tb_phase (v2 - 올바른 파라미터)
// Description : Phase-based Attention 검증
//
// [v2 수정]
//   핵심 원리 재정립:
//   
//   위상 코딩의 동작 조건:
//     input_current << THRESHOLD 여야 함
//     → 여러 클럭 누적 후 발화
//     → 강한 입력 = 빨리 누적 = 낮은 위상
//     → 약한 입력 = 천천히 누적 = 높은 위상
//
//   파라미터:
//     THRESHOLD = 200 (높게)
//     입력 범위 = 1~50 (낮게)
//     → 4~200 클럭 후 발화 → 위상 차이 명확
//
//   [예시]
//   input=50: 200/50 = 4클럭 후 발화 → phase≈4
//   input=10: 200/10 = 20클럭 후 발화 → phase≈20
//   input=2:  200/2  = 100클럭 후 발화 → phase≈100
//   input=1:  200/1  = 200클럭 후 발화 → phase≈200
//   input=0:  발화 안 함
// =============================================================================
`timescale 1ns / 1ps

module tb_phase;

    reg clk, rst_n;
    initial clk = 0;
    always #5 clk = ~clk;

    wire [7:0] gphase;
    wire       cyc_start;

    gamma_oscillator #(.CYCLE_LEN(9'd256)) osc (
        .clk(clk), .rst_n(rst_n),
        .phase_out(gphase), .cycle_start(cyc_start)
    );

    // THRESHOLD=200, LEAK=0, 입력은 소전류
    reg [7:0] cur_a, cur_b, cur_c;
    wire spk_a, spk_b, spk_c;
    wire [7:0] ph_a, ph_b, ph_c;
    wire fired_a, fired_b, fired_c;

    phase_neuron #(.THRESHOLD(8'd200), .LEAK(8'd0), .CYCLE_LEN(8'd255)) nA (
        .clk(clk), .rst_n(rst_n), .global_phase(gphase), .cycle_start(cyc_start),
        .input_current(cur_a), .spike_out(spk_a),
        .phase_lock(ph_a), .fired_this_cycle(fired_a));

    phase_neuron #(.THRESHOLD(8'd200), .LEAK(8'd0), .CYCLE_LEN(8'd255)) nB (
        .clk(clk), .rst_n(rst_n), .global_phase(gphase), .cycle_start(cyc_start),
        .input_current(cur_b), .spike_out(spk_b),
        .phase_lock(ph_b), .fired_this_cycle(fired_b));

    phase_neuron #(.THRESHOLD(8'd200), .LEAK(8'd0), .CYCLE_LEN(8'd255)) nC (
        .clk(clk), .rst_n(rst_n), .global_phase(gphase), .cycle_start(cyc_start),
        .input_current(cur_c), .spike_out(spk_c),
        .phase_lock(ph_c), .fired_this_cycle(fired_c));

    // A vs B
    wire [7:0] rel_ab; wire coin_ab;
    coincidence_detector #(.PHASE_TOL(8'd20)) cd_ab (
        .clk(clk), .rst_n(rst_n),
        .fired_a(fired_a), .fired_b(fired_b),
        .phase_a(ph_a), .phase_b(ph_b),
        .cycle_start(cyc_start),
        .relevance(rel_ab), .coincident(coin_ab));

    // A vs C
    wire [7:0] rel_ac; wire coin_ac;
    coincidence_detector #(.PHASE_TOL(8'd20)) cd_ac (
        .clk(clk), .rst_n(rst_n),
        .fired_a(fired_a), .fired_b(fired_c),
        .phase_a(ph_a), .phase_b(ph_c),
        .cycle_start(cyc_start),
        .relevance(rel_ac), .coincident(coin_ac));

    // Result output
    reg [7:0] diff_ab, diff_ac, rel_ab_now, rel_ac_now;
    wire fa = (ph_a != 8'd255);  // fired if phase_lock != 255 (default)
    wire fb = (ph_b != 8'd255);
    wire fc = (ph_c != 8'd255);

    always @(posedge clk) begin
        if (spk_a) $display("  [A fired] phase=%3d", gphase);
        if (spk_b) $display("  [B fired] phase=%3d", gphase);
        if (spk_c) $display("  [C fired] phase=%3d", gphase);

        if (gphase == 8'd254) begin
            // circular diff A-B
            diff_ab = (ph_a >= ph_b) ? (ph_a - ph_b) : (ph_b - ph_a);
            if (diff_ab > 8'd128) diff_ab = 8'd255 - diff_ab;
            rel_ab_now = 8'd255 - diff_ab;

            // circular diff A-C
            diff_ac = (ph_a >= ph_c) ? (ph_a - ph_c) : (ph_c - ph_a);
            if (diff_ac > 8'd128) diff_ac = 8'd255 - diff_ac;
            rel_ac_now = 8'd255 - diff_ac;

            $display("  [cycle] phA=%3d(f=%b) phB=%3d(f=%b) phC=%3d(f=%b)",
                     ph_a, fa, ph_b, fb, ph_c, fc);
            if (fa && fb)
                $display("    A vs B: diff=%3d  Rel=%3d  Coin=%b  [%s]",
                    diff_ab, rel_ab_now,
                    (diff_ab <= 8'd20) ? 1'b1 : 1'b0,
                    (diff_ab <= 8'd20) ? "RELATED" : "UNRELATED");
            if (fa && fc)
                $display("    A vs C: diff=%3d  Rel=%3d  Coin=%b  [%s]",
                    diff_ac, rel_ac_now,
                    (diff_ac <= 8'd20) ? 1'b1 : 1'b0,
                    (diff_ac <= 8'd20) ? "RELATED" : "UNRELATED");
        end
    end


    initial begin
        $dumpfile("phase_dump.vcd");
        $dumpvars(0, tb_phase);
        rst_n=0; cur_a=0; cur_b=0; cur_c=0;
        repeat(3) @(posedge clk); #1; rst_n=1;

        // ─────────────────────────────────────────────────────
        // [Test 1] A=강(50/사이클) vs B=강(45/사이클)
        //   → 둘 다 위상 초반 발화 → 관련성 높음
        // ─────────────────────────────────────────────────────
        $display("\n=== [Test 1] A=50(강) vs B=45(강) → 관련성 높음 기대 ===");
        $display("  예상: A≈phase4, B≈phase4 → Rel 높음");
        cur_a=8'd50; cur_b=8'd45; cur_c=8'd0;
        repeat(512) @(posedge clk); #1;

        // ─────────────────────────────────────────────────────
        // [Test 2] A=강(50) vs C=약(5)
        //   → A는 위상 4, C는 위상 40 → 관련성 낮음
        // ─────────────────────────────────────────────────────
        $display("\n=== [Test 2] A=50(강) vs C=5(약) → 관련성 낮음 기대 ===");
        $display("  예상: A≈phase4, C≈phase40 → Rel 낮음");
        cur_a=8'd50; cur_b=8'd0; cur_c=8'd5;
        repeat(512) @(posedge clk); #1;

        // ─────────────────────────────────────────────────────
        // [Test 3] A=중(20) vs B=중(22)
        //   → 비슷한 위상 → 관련성 높음
        // ─────────────────────────────────────────────────────
        $display("\n=== [Test 3] A=20(중) vs B=22(중) → 관련성 높음 기대 ===");
        $display("  예상: A≈phase10, B≈phase9 → Rel 높음");
        cur_a=8'd20; cur_b=8'd22; cur_c=8'd0;
        repeat(512) @(posedge clk); #1;

        // ─────────────────────────────────────────────────────
        // [Test 4] A=강(50) vs B=약(5) → 관련성 낮음
        // ─────────────────────────────────────────────────────
        $display("\n=== [Test 4] A=50(강) vs B=5(약) → 관련성 낮음 기대 ===");
        $display("  예상: A≈phase4, B≈phase40 → Rel 낮음");
        cur_a=8'd50; cur_b=8'd5; cur_c=8'd0;
        repeat(512) @(posedge clk); #1;

        $display("\n=== [완료] ===");
        $finish;
    end

endmodule

phase_dump.vcd
$date
	Wed Feb 18 12:26:24 2026
$end
$version
	Icarus Verilog
$end
$timescale
	1ps
$end
$scope module tb_phase $end
$var wire 1 ! spk_c $end
$var wire 1 " spk_b $end
$var wire 1 # spk_a $end
$var wire 8 $ rel_ac [7:0] $end
$var wire 8 % rel_ab [7:0] $end
$var wire 8 & ph_c [7:0] $end
$var wire 8 ' ph_b [7:0] $end
$var wire 8 ( ph_a [7:0] $end
$var wire 8 ) gphase [7:0] $end
$var wire 1 * fired_c $end
$var wire 1 + fired_b $end
$var wire 1 , fired_a $end
$var wire 1 - fc $end
$var wire 1 . fb $end
$var wire 1 / fa $end
$var wire 1 0 cyc_start $end
$var wire 1 1 coin_ac $end
$var wire 1 2 coin_ab $end
$var reg 1 3 clk $end
$var reg 8 4 cur_a [7:0] $end
$var reg 8 5 cur_b [7:0] $end
$var reg 8 6 cur_c [7:0] $end
$var reg 8 7 diff_ab [7:0] $end
$var reg 8 8 diff_ac [7:0] $end
$var reg 8 9 rel_ab_now [7:0] $end
$var reg 8 : rel_ac_now [7:0] $end
$var reg 1 ; rst_n $end
$scope module cd_ab $end
$var wire 1 3 clk $end
$var wire 1 ; rst_n $end
$var wire 8 < rel_score [7:0] $end
$var wire 8 = phase_diff [7:0] $end
$var wire 8 > phase_b [7:0] $end
$var wire 8 ? phase_a [7:0] $end
$var wire 9 @ pb [8:0] $end
$var wire 9 A pa [8:0] $end
$var wire 1 + fired_b $end
$var wire 1 , fired_a $end
$var wire 9 B diff_wrap [8:0] $end
$var wire 9 C diff_raw [8:0] $end
$var wire 1 0 cycle_start $end
$var reg 1 2 coincident $end
$var reg 8 D relevance [7:0] $end
$upscope $end
$scope module cd_ac $end
$var wire 1 3 clk $end
$var wire 1 ; rst_n $end
$var wire 8 E rel_score [7:0] $end
$var wire 8 F phase_diff [7:0] $end
$var wire 8 G phase_b [7:0] $end
$var wire 8 H phase_a [7:0] $end
$var wire 9 I pb [8:0] $end
$var wire 9 J pa [8:0] $end
$var wire 1 * fired_b $end
$var wire 1 , fired_a $end
$var wire 9 K diff_wrap [8:0] $end
$var wire 9 L diff_raw [8:0] $end
$var wire 1 0 cycle_start $end
$var reg 1 1 coincident $end
$var reg 8 M relevance [7:0] $end
$upscope $end
$scope module nA $end
$var wire 1 3 clk $end
$var wire 8 N input_current [7:0] $end
$var wire 1 ; rst_n $end
$var wire 8 O global_phase [7:0] $end
$var wire 1 0 cycle_start $end
$var reg 1 , fired_this_cycle $end
$var reg 1 P has_fired $end
$var reg 8 Q phase_lock [7:0] $end
$var reg 1 # spike_out $end
$var reg 8 R v_mem [7:0] $end
$var reg 9 S v_next [8:0] $end
$upscope $end
$scope module nB $end
$var wire 1 3 clk $end
$var wire 8 T input_current [7:0] $end
$var wire 1 ; rst_n $end
$var wire 8 U global_phase [7:0] $end
$var wire 1 0 cycle_start $end
$var reg 1 + fired_this_cycle $end
$var reg 1 V has_fired $end
$var reg 8 W phase_lock [7:0] $end
$var reg 1 " spike_out $end
$var reg 8 X v_mem [7:0] $end
$var reg 9 Y v_next [8:0] $end
$upscope $end
$scope module nC $end
$var wire 1 3 clk $end
$var wire 8 Z input_current [7:0] $end
$var wire 1 ; rst_n $end
$var wire 8 [ global_phase [7:0] $end
$var wire 1 0 cycle_start $end
$var reg 1 * fired_this_cycle $end
$var reg 1 \ has_fired $end
$var reg 8 ] phase_lock [7:0] $end
$var reg 1 ! spike_out $end
$var reg 8 ^ v_mem [7:0] $end
$var reg 9 _ v_next [8:0] $end
$upscope $end
$scope module osc $end
$var wire 1 3 clk $end
$var wire 1 ; rst_n $end
$var reg 1 0 cycle_start $end
$var reg 8 ` phase_out [7:0] $end
$upscope $end
$upscope $end
$enddefinitions $end
#0
$dumpvars
b0 `
b0 _
b0 ^
b11111111 ]
0\
b0 [
b0 Z
b0 Y
b0 X
b11111111 W
0V
b0 U
b0 T
b0 S
b0 R
b11111111 Q
0P
b0 O
b0 N
b0 M
b0 L
b100000000 K
b11111111 J
b11111111 I
b11111111 H
b11111111 G
b0 F
b11111111 E
b0 D
b0 C
b100000000 B
b11111111 A
b11111111 @
b11111111 ?
b11111111 >
b0 =
b11111111 <
0;
bx :
bx 9
bx 8
bx 7
b0 6
b0 5
b0 4
03
02
01
00
0/
0.
0-
0,
0+
0*
b0 )
b11111111 (
b11111111 '
b11111111 &
b0 %
b0 $
0#
0"
0!
$end
#5000
13
#10000
03
#15000
13
#20000
03
#25000
13
#26000
b101101 5
b101101 T
b110010 4
b110010 N
1;
#30000
03
#35000
b1 )
b1 O
b1 U
b1 [
b1 `
b110010 R
b101101 X
b110010 S
b101101 Y
13
#40000
03
#45000
b1011010 X
b1100100 R
b10 )
b10 O
b10 U
b10 [
b10 `
b1011010 Y
b1100100 S
13
#50000
03
#55000
b11 )
b11 O
b11 U
b11 [
b11 `
b10010110 R
b10000111 X
b10010110 S
b10000111 Y
13
#60000
03
#65000
b11111011 E
b100 F
b11111011 <
b100 =
b100 K
b11111100 L
b100 B
b11111100 C
b10110100 X
1P
1,
b11 J
b11 A
1/
b11 (
b11 ?
b11 H
b11 Q
1#
b0 R
b100 )
b100 O
b100 U
b100 [
b100 `
b10110100 Y
b11001000 S
13
#70000
03
#75000
b11111110 <
b1 =
b11111111 B
b1 C
b101 )
b101 O
b101 U
b101 [
b101 `
0#
1V
1+
b100 @
1.
b100 '
b100 >
b100 W
1"
b0 X
b11100001 Y
13
#80000
03
#85000
0"
b110 )
b110 O
b110 U
b110 [
b110 `
13
#90000
03
#95000
b111 )
b111 O
b111 U
b111 [
b111 `
13
#100000
03
#105000
b1000 )
b1000 O
b1000 U
b1000 [
b1000 `
13
#110000
03
#115000
b1001 )
b1001 O
b1001 U
b1001 [
b1001 `
13
#120000
03
#125000
b1010 )
b1010 O
b1010 U
b1010 [
b1010 `
13
#130000
03
#135000
b1011 )
b1011 O
b1011 U
b1011 [
b1011 `
13
#140000
03
#145000
b1100 )
b1100 O
b1100 U
b1100 [
b1100 `
13
#150000
03
#155000
b1101 )
b1101 O
b1101 U
b1101 [
b1101 `
13
#160000
03
#165000
b1110 )
b1110 O
b1110 U
b1110 [
b1110 `
13
#170000
03
#175000
b1111 )
b1111 O
b1111 U
b1111 [
b1111 `
13
#180000
03
#185000
b10000 )
b10000 O
b10000 U
b10000 [
b10000 `
13
#190000
03
#195000
b10001 )
b10001 O
b10001 U
b10001 [
b10001 `
13
#200000
03
#205000
b10010 )
b10010 O
b10010 U
b10010 [
b10010 `
13
#210000
03
#215000
b10011 )
b10011 O
b10011 U
b10011 [
b10011 `
13
#220000
03
#225000
b10100 )
b10100 O
b10100 U
b10100 [
b10100 `
13
#230000
03
#235000
b10101 )
b10101 O
b10101 U
b10101 [
b10101 `
13
#240000
03
#245000
b10110 )
b10110 O
b10110 U
b10110 [
b10110 `
13
#250000
03
#255000
b10111 )
b10111 O
b10111 U
b10111 [
b10111 `
13
#260000
03
#265000
b11000 )
b11000 O
b11000 U
b11000 [
b11000 `
13
#270000
03
#275000
b11001 )
b11001 O
b11001 U
b11001 [
b11001 `
13
#280000
03
#285000
b11010 )
b11010 O
b11010 U
b11010 [
b11010 `
13
#290000
03
#295000
b11011 )
b11011 O
b11011 U
b11011 [
b11011 `
13
#300000
03
#305000
b11100 )
b11100 O
b11100 U
b11100 [
b11100 `
13
#310000
03
#315000
b11101 )
b11101 O
b11101 U
b11101 [
b11101 `
13
#320000
03
#325000
b11110 )
b11110 O
b11110 U
b11110 [
b11110 `
13
#330000
03
#335000
b11111 )
b11111 O
b11111 U
b11111 [
b11111 `
13
#340000
03
#345000
b100000 )
b100000 O
b100000 U
b100000 [
b100000 `
13
#350000
03
#355000
b100001 )
b100001 O
b100001 U
b100001 [
b100001 `
13
#360000
03
#365000
b100010 )
b100010 O
b100010 U
b100010 [
b100010 `
13
#370000
03
#375000
b100011 )
b100011 O
b100011 U
b100011 [
b100011 `
13
#380000
03
#385000
b100100 )
b100100 O
b100100 U
b100100 [
b100100 `
13
#390000
03
#395000
b100101 )
b100101 O
b100101 U
b100101 [
b100101 `
13
#400000
03
#405000
b100110 )
b100110 O
b100110 U
b100110 [
b100110 `
13
#410000
03
#415000
b100111 )
b100111 O
b100111 U
b100111 [
b100111 `
13
#420000
03
#425000
b101000 )
b101000 O
b101000 U
b101000 [
b101000 `
13
#430000
03
#435000
b101001 )
b101001 O
b101001 U
b101001 [
b101001 `
13
#440000
03
#445000
b101010 )
b101010 O
b101010 U
b101010 [
b101010 `
13
#450000
03
#455000
b101011 )
b101011 O
b101011 U
b101011 [
b101011 `
13
#460000
03
#465000
b101100 )
b101100 O
b101100 U
b101100 [
b101100 `
13
#470000
03
#475000
b101101 )
b101101 O
b101101 U
b101101 [
b101101 `
13
#480000
03
#485000
b101110 )
b101110 O
b101110 U
b101110 [
b101110 `
13
#490000
03
#495000
b101111 )
b101111 O
b101111 U
b101111 [
b101111 `
13
#500000
03
#505000
b110000 )
b110000 O
b110000 U
b110000 [
b110000 `
13
#510000
03
#515000
b110001 )
b110001 O
b110001 U
b110001 [
b110001 `
13
#520000
03
#525000
b110010 )
b110010 O
b110010 U
b110010 [
b110010 `
13
#530000
03
#535000
b110011 )
b110011 O
b110011 U
b110011 [
b110011 `
13
#540000
03
#545000
b110100 )
b110100 O
b110100 U
b110100 [
b110100 `
13
#550000
03
#555000
b110101 )
b110101 O
b110101 U
b110101 [
b110101 `
13
#560000
03
#565000
b110110 )
b110110 O
b110110 U
b110110 [
b110110 `
13
#570000
03
#575000
b110111 )
b110111 O
b110111 U
b110111 [
b110111 `
13
#580000
03
#585000
b111000 )
b111000 O
b111000 U
b111000 [
b111000 `
13
#590000
03
#595000
b111001 )
b111001 O
b111001 U
b111001 [
b111001 `
13
#600000
03
#605000
b111010 )
b111010 O
b111010 U
b111010 [
b111010 `
13
#610000
03
#615000
b111011 )
b111011 O
b111011 U
b111011 [
b111011 `
13
#620000
03
#625000
b111100 )
b111100 O
b111100 U
b111100 [
b111100 `
13
#630000
03
#635000
b111101 )
b111101 O
b111101 U
b111101 [
b111101 `
13
#640000
03
#645000
b111110 )
b111110 O
b111110 U
b111110 [
b111110 `
13
#650000
03
#655000
b111111 )
b111111 O
b111111 U
b111111 [
b111111 `
13
#660000
03
#665000
b1000000 )
b1000000 O
b1000000 U
b1000000 [
b1000000 `
13
#670000
03
#675000
b1000001 )
b1000001 O
b1000001 U
b1000001 [
b1000001 `
13
#680000
03
#685000
b1000010 )
b1000010 O
b1000010 U
b1000010 [
b1000010 `
13
#690000
03
#695000
b1000011 )
b1000011 O
b1000011 U
b1000011 [
b1000011 `
13
#700000
03
#705000
b1000100 )
b1000100 O
b1000100 U
b1000100 [
b1000100 `
13
#710000
03
#715000
b1000101 )
b1000101 O
b1000101 U
b1000101 [
b1000101 `
13
#720000
03
#725000
b1000110 )
b1000110 O
b1000110 U
b1000110 [
b1000110 `
13
#730000
03
#735000
b1000111 )
b1000111 O
b1000111 U
b1000111 [
b1000111 `
13
#740000
03
#745000
b1001000 )
b1001000 O
b1001000 U
b1001000 [
b1001000 `
13
#750000
03
#755000
b1001001 )
b1001001 O
b1001001 U
b1001001 [
b1001001 `
13
#760000
03
#765000
b1001010 )
b1001010 O
b1001010 U
b1001010 [
b1001010 `
13
#770000
03
#775000
b1001011 )
b1001011 O
b1001011 U
b1001011 [
b1001011 `
13
#780000
03
#785000
b1001100 )
b1001100 O
b1001100 U
b1001100 [
b1001100 `
13
#790000
03
#795000
b1001101 )
b1001101 O
b1001101 U
b1001101 [
b1001101 `
13
#800000
03
#805000
b1001110 )
b1001110 O
b1001110 U
b1001110 [
b1001110 `
13
#810000
03
#815000
b1001111 )
b1001111 O
b1001111 U
b1001111 [
b1001111 `
13
#820000
03
#825000
b1010000 )
b1010000 O
b1010000 U
b1010000 [
b1010000 `
13
#830000
03
#835000
b1010001 )
b1010001 O
b1010001 U
b1010001 [
b1010001 `
13
#840000
03
#845000
b1010010 )
b1010010 O
b1010010 U
b1010010 [
b1010010 `
13
#850000
03
#855000
b1010011 )
b1010011 O
b1010011 U
b1010011 [
b1010011 `
13
#860000
03
#865000
b1010100 )
b1010100 O
b1010100 U
b1010100 [
b1010100 `
13
#870000
03
#875000
b1010101 )
b1010101 O
b1010101 U
b1010101 [
b1010101 `
13
#880000
03
#885000
b1010110 )
b1010110 O
b1010110 U
b1010110 [
b1010110 `
13
#890000
03
#895000
b1010111 )
b1010111 O
b1010111 U
b1010111 [
b1010111 `
13
#900000
03
#905000
b1011000 )
b1011000 O
b1011000 U
b1011000 [
b1011000 `
13
#910000
03
#915000
b1011001 )
b1011001 O
b1011001 U
b1011001 [
b1011001 `
13
#920000
03
#925000
b1011010 )
b1011010 O
b1011010 U
b1011010 [
b1011010 `
13
#930000
03
#935000
b1011011 )
b1011011 O
b1011011 U
b1011011 [
b1011011 `
13
#940000
03
#945000
b1011100 )
b1011100 O
b1011100 U
b1011100 [
b1011100 `
13
#950000
03
#955000
b1011101 )
b1011101 O
b1011101 U
b1011101 [
b1011101 `
13
#960000
03
#965000
b1011110 )
b1011110 O
b1011110 U
b1011110 [
b1011110 `
13
#970000
03
#975000
b1011111 )
b1011111 O
b1011111 U
b1011111 [
b1011111 `
13
#980000
03
#985000
b1100000 )
b1100000 O
b1100000 U
b1100000 [
b1100000 `
13
#990000
03
#995000
b1100001 )
b1100001 O
b1100001 U
b1100001 [
b1100001 `
13
#1000000
03
#1005000
b1100010 )
b1100010 O
b1100010 U
b1100010 [
b1100010 `
13
#1010000
03
#1015000
b1100011 )
b1100011 O
b1100011 U
b1100011 [
b1100011 `
13
#1020000
03
#1025000
b1100100 )
b1100100 O
b1100100 U
b1100100 [
b1100100 `
13
#1030000
03
#1035000
b1100101 )
b1100101 O
b1100101 U
b1100101 [
b1100101 `
13
#1040000
03
#1045000
b1100110 )
b1100110 O
b1100110 U
b1100110 [
b1100110 `
13
#1050000
03
#1055000
b1100111 )
b1100111 O
b1100111 U
b1100111 [
b1100111 `
13
#1060000
03
#1065000
b1101000 )
b1101000 O
b1101000 U
b1101000 [
b1101000 `
13
#1070000
03
#1075000
b1101001 )
b1101001 O
b1101001 U
b1101001 [
b1101001 `
13
#1080000
03
#1085000
b1101010 )
b1101010 O
b1101010 U
b1101010 [
b1101010 `
13
#1090000
03
#1095000
b1101011 )
b1101011 O
b1101011 U
b1101011 [
b1101011 `
13
#1100000
03
#1105000
b1101100 )
b1101100 O
b1101100 U
b1101100 [
b1101100 `
13
#1110000
03
#1115000
b1101101 )
b1101101 O
b1101101 U
b1101101 [
b1101101 `
13
#1120000
03
#1125000
b1101110 )
b1101110 O
b1101110 U
b1101110 [
b1101110 `
13
#1130000
03
#1135000
b1101111 )
b1101111 O
b1101111 U
b1101111 [
b1101111 `
13
#1140000
03
#1145000
b1110000 )
b1110000 O
b1110000 U
b1110000 [
b1110000 `
13
#1150000
03
#1155000
b1110001 )
b1110001 O
b1110001 U
b1110001 [
b1110001 `
13
#1160000
03
#1165000
b1110010 )
b1110010 O
b1110010 U
b1110010 [
b1110010 `
13
#1170000
03
#1175000
b1110011 )
b1110011 O
b1110011 U
b1110011 [
b1110011 `
13
#1180000
03
#1185000
b1110100 )
b1110100 O
b1110100 U
b1110100 [
b1110100 `
13
#1190000
03
#1195000
b1110101 )
b1110101 O
b1110101 U
b1110101 [
b1110101 `
13
#1200000
03
#1205000
b1110110 )
b1110110 O
b1110110 U
b1110110 [
b1110110 `
13
#1210000
03
#1215000
b1110111 )
b1110111 O
b1110111 U
b1110111 [
b1110111 `
13
#1220000
03
#1225000
b1111000 )
b1111000 O
b1111000 U
b1111000 [
b1111000 `
13
#1230000
03
#1235000
b1111001 )
b1111001 O
b1111001 U
b1111001 [
b1111001 `
13
#1240000
03
#1245000
b1111010 )
b1111010 O
b1111010 U
b1111010 [
b1111010 `
13
#1250000
03
#1255000
b1111011 )
b1111011 O
b1111011 U
b1111011 [
b1111011 `
13
#1260000
03
#1265000
b1111100 )
b1111100 O
b1111100 U
b1111100 [
b1111100 `
13
#1270000
03
#1275000
b1111101 )
b1111101 O
b1111101 U
b1111101 [
b1111101 `
13
#1280000
03
#1285000
b1111110 )
b1111110 O
b1111110 U
b1111110 [
b1111110 `
13
#1290000
03
