synapse_da.v
// =============================================================================
// Module  : synapse_da
// Project : HNSN - Phase 5: Neuromodulation (도파민 조절 시냅스)
//
// Description:
//   기존 STDP 시냅스에 도파민(Dopamine) 신호를 추가한 확장 버전.
//   뇌의 보상 회로(Reward Circuit)를 모사.
//
//   [생물학적 배경]
//   도파민은 "보상 예측 오류(Reward Prediction Error)" 신호.
//   - 예상보다 좋은 일 발생 → 도파민 급증 → 시냅스 강하게 강화
//   - 예상보다 나쁜 일 발생 → 도파민 감소 → 시냅스 약화
//   - 예상대로 → 도파민 변화 없음 → 시냅스 유지
//
//   [하드웨어 구현]
//   기존 STDP:  weight += LTP_STEP (고정)
//   DA-STDP:    weight += LTP_STEP * dopamine_level (가변)
//
//   dopamine_level [1:0]:
//     2'b00 = 도파민 없음  → 학습 억제 (LTP/LTD 모두 절반)
//     2'b01 = 기본 도파민  → 일반 STDP (기존과 동일)
//     2'b10 = 높은 도파민  → 강화 학습 (LTP 2배, LTD 절반)
//     2'b11 = 최대 도파민  → 강력 강화 (LTP 3배, LTD 없음)
//
//   이를 통해 "보상이 있을 때만 강하게 학습" 구현
// =============================================================================

module synapse_da #(
    parameter [7:0] INIT_WEIGHT  = 8'd10,
    parameter [7:0] MAX_WEIGHT   = 8'd255,
    parameter [7:0] MIN_WEIGHT   = 8'd0,
    parameter [7:0] LTP_STEP     = 8'd2,
    parameter [7:0] LTD_STEP     = 8'd1,
    parameter [3:0] TRACE_DECAY  = 4'd8
)(
    input  wire       clk,
    input  wire       rst_n,
    input  wire       pre_spike,
    input  wire       post_spike,
    input  wire [1:0] dopamine_level,   // 도파민 농도 (00~11)

    output wire [7:0] weighted_current,
    output wire [7:0] weight
);

    reg [7:0] weight_reg;
    reg [3:0] pre_trace;
    reg [3:0] post_trace;

    // -------------------------------------------------------------------------
    // 도파민 레벨에 따른 LTP/LTD 스텝 조절
    // -------------------------------------------------------------------------
    reg [7:0] ltp_effective;
    reg [7:0] ltd_effective;

    always @(*) begin
        case (dopamine_level)
            2'b00: begin  // 도파민 없음: 학습 억제
                ltp_effective = LTP_STEP >> 1;   // LTP 절반
                ltd_effective = LTD_STEP;         // LTD 유지 (망각)
            end
            2'b01: begin  // 기본: 일반 STDP
                ltp_effective = LTP_STEP;
                ltd_effective = LTD_STEP;
            end
            2'b10: begin  // 높은 도파민: 강화 학습
                ltp_effective = LTP_STEP << 1;   // LTP 2배
                ltd_effective = LTD_STEP >> 1;   // LTD 절반
            end
            2'b11: begin  // 최대 도파민: 강력 강화
                ltp_effective = LTP_STEP + (LTP_STEP << 1); // LTP 3배
                ltd_effective = 8'd0;             // LTD 없음 (완전 강화)
            end
        endcase
    end

    // -------------------------------------------------------------------------
    // 가중치 업데이트 (오버플로우/언더플로우 방지)
    // -------------------------------------------------------------------------
    wire [8:0] weight_ltp = {1'b0, weight_reg} + {1'b0, ltp_effective};
    wire [8:0] weight_ltd = {1'b0, weight_reg} - {1'b0, ltd_effective};

    wire [7:0] weight_after_ltp =
        (weight_ltp > {1'b0, MAX_WEIGHT}) ? MAX_WEIGHT : weight_ltp[7:0];
    wire [7:0] weight_after_ltd =
        weight_ltd[8] ? MIN_WEIGHT : weight_ltd[7:0];

    // -------------------------------------------------------------------------
    // 순차 논리
    // -------------------------------------------------------------------------
    always @(posedge clk or negedge rst_n) begin
        if (!rst_n) begin
            weight_reg <= INIT_WEIGHT;
            pre_trace  <= 4'd0;
            post_trace <= 4'd0;
        end
        else begin
            // 트레이스 업데이트
            if (pre_spike)        pre_trace <= TRACE_DECAY;
            else if (pre_trace > 0) pre_trace <= pre_trace - 4'd1;

            if (post_spike)        post_trace <= TRACE_DECAY;
            else if (post_trace > 0) post_trace <= post_trace - 4'd1;

            // DA-STDP 가중치 업데이트
            if (post_spike && (pre_trace > 4'd0))
                weight_reg <= weight_after_ltp;   // LTP (도파민 조절)
            else if (pre_spike && (post_trace > 4'd0))
                weight_reg <= weight_after_ltd;   // LTD (도파민 조절)
        end
    end

    assign weighted_current = pre_spike ? weight_reg : 8'd0;
    assign weight           = weight_reg;

endmodule
// =============================================================================
// End of synapse_da.v
// =============================================================================

reward_circuit.v
// =============================================================================
// Module  : reward_circuit (v2 - 소거 버그 수정)
// Project : HNSN - Phase 5: Neuromodulation
//
// [v2 수정 사항]
//   - reward_count 감소를 매 클럭이 아닌 DECAY_RATE 클럭마다 1씩 감소
//     → predict_state가 너무 빨리 해제되는 버그 수정
//   - predict_state 해제 조건: reward_count가 완전히 0이 될 때만
//
// [보상 예측 오류 (RPE) 로직]
//   reward=1, prediction=0 → 예상 밖 보상 → dopamine=11 (최대)
//   reward=1, prediction=1 → 예상된 보상  → dopamine=01 (기본)
//   reward=0, prediction=0 → 보상 없음    → dopamine=01 (기본)
//   reward=0, prediction=1 → 예상 보상 없음→ dopamine=00 (억제)
// =============================================================================

module reward_circuit #(
    parameter [3:0] PREDICT_THRESH = 4'd5, // 연속 보상 횟수 → 예측 상태 전환
    parameter [3:0] DECAY_RATE     = 4'd8  // 카운터 감소 속도 (클럭/1감소)
)(
    input  wire       clk,
    input  wire       rst_n,
    input  wire       reward,

    output reg  [1:0] dopamine_level,
    output wire       prediction
);

    reg [3:0] reward_count;   // 연속 보상 카운터
    reg [3:0] decay_counter;  // 감소 속도 조절용 카운터
    reg       predict_state;

    assign prediction = predict_state;

    always @(posedge clk or negedge rst_n) begin
        if (!rst_n) begin
            reward_count   <= 4'd0;
            decay_counter  <= 4'd0;
            predict_state  <= 1'b0;
            dopamine_level <= 2'b01;
        end
        else begin
            // -----------------------------------------------------------------
            // 예측 상태 업데이트
            // -----------------------------------------------------------------
            if (reward) begin
                // 보상 있음: 카운터 빠르게 증가
                decay_counter <= 4'd0;  // 감소 타이머 리셋
                if (reward_count < PREDICT_THRESH)
                    reward_count <= reward_count + 4'd1;
                else
                    predict_state <= 1'b1;
            end
            else begin
                // 보상 없음: DECAY_RATE 클럭마다 카운터 1 감소
                if (decay_counter < DECAY_RATE) begin
                    decay_counter <= decay_counter + 4'd1;
                end
                else begin
                    decay_counter <= 4'd0;
                    if (reward_count > 4'd0)
                        reward_count <= reward_count - 4'd1;
                end
                // 카운터가 완전히 소진되면 예측 상태 해제
                if (reward_count == 4'd0)
                    predict_state <= 1'b0;
            end

            // -----------------------------------------------------------------
            // 도파민 레벨 결정
            // -----------------------------------------------------------------
            case ({reward, predict_state})
                2'b10: dopamine_level <= 2'b11; // 예상 밖 보상 → 최대
                2'b11: dopamine_level <= 2'b01; // 예상된 보상  → 기본
                2'b00: dopamine_level <= 2'b01; // 보상 없음    → 기본
                2'b01: dopamine_level <= 2'b00; // 예상 배반    → 억제
            endcase
        end
    end

endmodule
// =============================================================================
// End of reward_circuit.v (v2)
// =============================================================================

tb_reward.v
// =============================================================================
// Module  : tb_reward
// Description : 도파민 보상 회로 + DA-STDP 시냅스 통합 검증
//
// [검증 시나리오]
//
// [Phase A] 보상 없이 학습 → weight 느리게 증가
// [Phase B] 보상 신호 추가 → dopamine=11 → weight 빠르게 증가
// [Phase C] 보상 반복 → predict_state=1 → dopamine=01 (기본으로 복귀)
// [Phase D] 보상 중단 (예측 배반) → dopamine=00 → weight 감소
//
// [관전 포인트]
//   Phase A vs Phase B: weight 증가 속도 차이
//   Phase D: 예상 보상이 안 오면 weight가 줄어드는 것 (실망 반응)
// =============================================================================
`timescale 1ns / 1ps

module tb_reward;

    reg clk, rst_n;
    reg pre_spike, post_spike;
    reg reward_in;

    wire [1:0] dopamine;
    wire       prediction;
    wire [7:0] w_current, w_val;

    // 도파민 회로
    reward_circuit #(.PREDICT_THRESH(4'd4)) rc (
        .clk          (clk),
        .rst_n        (rst_n),
        .reward       (reward_in),
        .dopamine_level(dopamine),
        .prediction   (prediction)
    );

    // DA-STDP 시냅스
    synapse_da #(
        .INIT_WEIGHT (8'd10),
        .LTP_STEP    (8'd3),
        .LTD_STEP    (8'd1),
        .TRACE_DECAY (4'd8)
    ) syn (
        .clk             (clk),
        .rst_n           (rst_n),
        .pre_spike       (pre_spike),
        .post_spike      (post_spike),
        .dopamine_level  (dopamine),
        .weighted_current(w_current),
        .weight          (w_val)
    );

    initial clk = 0;
    always #5 clk = ~clk;

    // pre→post 순서로 스파이크 발생 (LTP 조건)
    task fire_ltp;
        begin
            @(posedge clk); #1; pre_spike = 1; post_spike = 0;
            @(posedge clk); #1; pre_spike = 0; post_spike = 0;
            @(posedge clk); #1; pre_spike = 0; post_spike = 1;
            @(posedge clk); #1; pre_spike = 0; post_spike = 0;
        end
    endtask

    integer i;
    initial begin
        $dumpfile("reward_dump.vcd");
        $dumpvars(0, tb_reward);

        rst_n = 0; pre_spike = 0; post_spike = 0; reward_in = 0;
        @(posedge clk); #1;
        @(posedge clk); #1;
        rst_n = 1;

        // =====================================================================
        // [Phase A] 보상 없이 LTP 10회
        //   dopamine=01(기본) → LTP_STEP=3 적용
        // =====================================================================
        $display("\n=== [Phase A] 보상 없이 학습 (dopamine=기본) ===");
        reward_in = 0;
        for (i = 0; i < 10; i = i + 1)
            fire_ltp();

        // =====================================================================
        // [Phase B] 보상 신호 ON + LTP 10회
        //   처음엔 예측 없음 → dopamine=11(최대) → LTP_STEP×3 적용
        //   weight가 Phase A보다 훨씬 빠르게 증가해야 함
        // =====================================================================
        $display("\n=== [Phase B] 보상 신호 ON (dopamine=최대) ===");
        reward_in = 1;
        for (i = 0; i < 10; i = i + 1)
            fire_ltp();

        // =====================================================================
        // [Phase C] 보상 반복 → predict_state 전환
        //   4회 이상 연속 보상 → predict_state=1
        //   → 이제 보상이 와도 dopamine=01(기본)으로 복귀
        //   "익숙해지면 흥분이 줄어드는" 습관화(Habituation)
        // =====================================================================
        $display("\n=== [Phase C] 보상 반복 → 예측 상태 전환 (습관화) ===");
        reward_in = 1;
        for (i = 0; i < 15; i = i + 1)
            fire_ltp();

        // =====================================================================
        // [Phase D] 보상 중단 (예측 배반)
        //   predict_state=1인데 reward=0 → dopamine=00(억제)
        //   → LTP 절반, LTD 유지 → weight 감소
        //   "기대했는데 안 오면 실망" = 소거(Extinction)
        // =====================================================================
        $display("\n=== [Phase D] 보상 중단 (실망 반응 - dopamine=억제) ===");
        reward_in = 0;
        for (i = 0; i < 10; i = i + 1)
            fire_ltp();

        $display("\n=== [시뮬레이션 완료] ===");
        $finish;
    end

    initial begin
        $monitor("T=%t | Pre=%b Post=%b | Reward=%b Predict=%b | DA=%b | Weight=%3d",
                 $time, pre_spike, post_spike,
                 reward_in, prediction, dopamine, w_val);
    end

endmodule
// =============================================================================
// End of tb_reward.v
// =============================================================================

reward_dump.vcd
$date
	Wed Feb 18 11:14:34 2026
$end
$version
	Icarus Verilog
$end
$timescale
	1ps
$end
$scope module tb_reward $end
$var wire 8 ! w_val [7:0] $end
$var wire 8 " w_current [7:0] $end
$var wire 1 # prediction $end
$var wire 2 $ dopamine [1:0] $end
$var reg 1 % clk $end
$var reg 1 & post_spike $end
$var reg 1 ' pre_spike $end
$var reg 1 ( reward_in $end
$var reg 1 ) rst_n $end
$var integer 32 * i [31:0] $end
$scope module rc $end
$var wire 1 % clk $end
$var wire 1 # prediction $end
$var wire 1 ( reward $end
$var wire 1 ) rst_n $end
$var reg 4 + decay_counter [3:0] $end
$var reg 2 , dopamine_level [1:0] $end
$var reg 1 - predict_state $end
$var reg 4 . reward_count [3:0] $end
$upscope $end
$scope module syn $end
$var wire 1 % clk $end
$var wire 2 / dopamine_level [1:0] $end
$var wire 1 & post_spike $end
$var wire 1 ' pre_spike $end
$var wire 1 ) rst_n $end
$var wire 8 0 weight [7:0] $end
$var wire 8 1 weighted_current [7:0] $end
$var wire 9 2 weight_ltp [8:0] $end
$var wire 9 3 weight_ltd [8:0] $end
$var wire 8 4 weight_after_ltp [7:0] $end
$var wire 8 5 weight_after_ltd [7:0] $end
$var reg 8 6 ltd_effective [7:0] $end
$var reg 8 7 ltp_effective [7:0] $end
$var reg 4 8 post_trace [3:0] $end
$var reg 4 9 pre_trace [3:0] $end
$var reg 8 : weight_reg [7:0] $end
$upscope $end
$scope task fire_ltp $end
$upscope $end
$upscope $end
$enddefinitions $end
#0
$dumpvars
b1010 :
b0 9
b0 8
b11 7
b1 6
b1001 5
b1101 4
b1001 3
b1101 2
b0 1
b1010 0
b1 /
b0 .
0-
b1 ,
b0 +
bx *
0)
0(
0'
0&
0%
b1 $
0#
b0 "
b1010 !
$end
#5000
1%
#10000
0%
#15000
1%
#16000
b0 *
1)
#20000
0%
#25000
b1 +
1%
#26000
b1010 "
b1010 1
1'
#30000
0%
#35000
b10 +
b1000 9
1%
#36000
b0 "
b0 1
0'
#40000
0%
#45000
b111 9
b11 +
1%
#46000
1&
#50000
0%
#55000
b10000 4
b1100 5
b100 +
b10000 2
b1100 3
b1101 !
b1101 0
b1101 :
b1000 8
b110 9
1%
#56000
b1 *
0&
#60000
0%
#65000
b111 8
b101 9
b101 +
1%
#66000
b1101 "
b1101 1
1'
#70000
0%
#75000
b1111 4
b1011 5
b1100 "
b1100 1
b110 +
b1111 2
b1011 3
b1100 !
b1100 0
b1100 :
b110 8
b1000 9
1%
#76000
b0 "
b0 1
0'
#80000
0%
#85000
b101 8
b111 9
b111 +
1%
#86000
1&
#90000
0%
#95000
b10010 4
b1110 5
b1000 +
b10010 2
b1110 3
b1111 !
b1111 0
b1111 :
b1000 8
b110 9
1%
#96000
b10 *
0&
#100000
0%
#105000
b111 8
b101 9
b0 +
1%
#106000
b1111 "
b1111 1
1'
#110000
0%
#115000
b10001 4
b1101 5
b1110 "
b1110 1
b1 +
b10001 2
b1101 3
b1110 !
b1110 0
b1110 :
b110 8
b1000 9
1%
#116000
b0 "
b0 1
0'
#120000
0%
#125000
b101 8
b111 9
b10 +
1%
#126000
1&
#130000
0%
#135000
b10100 4
b10000 5
b11 +
b10100 2
b10000 3
b10001 !
b10001 0
b10001 :
b1000 8
b110 9
1%
#136000
b11 *
0&
#140000
0%
#145000
b111 8
b101 9
b100 +
1%
#146000
b10001 "
b10001 1
1'
#150000
0%
#155000
b10011 4
b1111 5
b10000 "
b10000 1
b101 +
b10011 2
b1111 3
b10000 !
b10000 0
b10000 :
b110 8
b1000 9
1%
#156000
b0 "
b0 1
0'
#160000
0%
#165000
b101 8
b111 9
b110 +
1%
#166000
1&
#170000
0%
#175000
b10110 4
b10010 5
b111 +
b10110 2
b10010 3
b10011 !
b10011 0
b10011 :
b1000 8
b110 9
1%
#176000
b100 *
0&
#180000
0%
#185000
b111 8
b101 9
b1000 +
1%
#186000
b10011 "
b10011 1
1'
#190000
0%
#195000
b10101 4
b10001 5
b10010 "
b10010 1
b0 +
b10101 2
b10001 3
b10010 !
b10010 0
b10010 :
b110 8
b1000 9
1%
#196000
b0 "
b0 1
0'
#200000
0%
#205000
b101 8
b111 9
b1 +
1%
#206000
1&
#210000
0%
#215000
b11000 4
b10100 5
b10 +
b11000 2
b10100 3
b10101 !
b10101 0
b10101 :
b1000 8
b110 9
1%
#216000
b101 *
0&
#220000
0%
#225000
b111 8
b101 9
b11 +
1%
#226000
b10101 "
b10101 1
1'
#230000
0%
#235000
b10111 4
b10011 5
b10100 "
b10100 1
b100 +
b10111 2
b10011 3
b10100 !
b10100 0
b10100 :
b110 8
b1000 9
1%
#236000
b0 "
b0 1
0'
#240000
0%
#245000
b101 8
b111 9
b101 +
1%
#246000
1&
#250000
0%
#255000
b11010 4
b10110 5
b110 +
b11010 2
b10110 3
b10111 !
b10111 0
b10111 :
b1000 8
b110 9
1%
#256000
b110 *
0&
#260000
0%
#265000
b111 8
b101 9
b111 +
1%
#266000
b10111 "
b10111 1
1'
#270000
0%
#275000
b11001 4
b10101 5
b10110 "
b10110 1
b1000 +
b11001 2
b10101 3
b10110 !
b10110 0
b10110 :
b110 8
b1000 9
1%
#276000
b0 "
b0 1
0'
#280000
0%
#285000
b101 8
b111 9
b0 +
1%
#286000
1&
#290000
0%
#295000
b11100 4
b11000 5
b1 +
b11100 2
b11000 3
b11001 !
b11001 0
b11001 :
b1000 8
b110 9
1%
#296000
b111 *
0&
#300000
0%
#305000
b111 8
b101 9
b10 +
1%
#306000
b11001 "
b11001 1
1'
#310000
0%
#315000
b11011 4
b10111 5
b11000 "
b11000 1
b11 +
b11011 2
b10111 3
b11000 !
b11000 0
b11000 :
b110 8
b1000 9
1%
#316000
b0 "
b0 1
0'
#320000
0%
#325000
b101 8
b111 9
b100 +
1%
#326000
1&
#330000
0%
#335000
b11110 4
b11010 5
b101 +
b11110 2
b11010 3
b11011 !
b11011 0
b11011 :
b1000 8
b110 9
1%
#336000
b1000 *
0&
#340000
0%
#345000
b111 8
b101 9
b110 +
1%
#346000
b11011 "
b11011 1
1'
#350000
0%
#355000
b11101 4
b11001 5
b11010 "
b11010 1
b111 +
b11101 2
b11001 3
b11010 !
b11010 0
b11010 :
b110 8
b1000 9
1%
#356000
b0 "
b0 1
0'
#360000
0%
#365000
b101 8
b111 9
b1000 +
1%
#366000
1&
#370000
0%
#375000
b100000 4
b11100 5
b0 +
b100000 2
b11100 3
b11101 !
b11101 0
b11101 :
b1000 8
b110 9
1%
#376000
b1001 *
0&
#380000
0%
#385000
b111 8
b101 9
b1 +
1%
#386000
b11101 "
b11101 1
1'
#390000
0%
#395000
b11111 4
b11011 5
b11100 "
b11100 1
b10 +
b11111 2
b11011 3
b11100 !
b11100 0
b11100 :
b110 8
b1000 9
1%
#396000
b0 "
b0 1
0'
#400000
0%
#405000
b101 8
b111 9
b11 +
1%
#406000
1&
#410000
0%
#415000
b100010 4
b11110 5
b100 +
b100010 2
b11110 3
b11111 !
b11111 0
b11111 :
b1000 8
b110 9
1%
#416000
1(
b0 *
0&
#420000
0%
#425000
b11111 5
b101000 4
b11111 3
b0 6
b101000 2
b1001 7
b111 8
b101 9
b11 $
b11 ,
b11 /
b1 .
b0 +
1%
#426000
b11111 "
b11111 1
1'
#430000
0%
#435000
b10 .
b110 8
b1000 9
1%
#436000
b0 "
b0 1
0'
#440000
0%
#445000
b101 8
b111 9
b11 .
1%
#446000
1&
#450000
0%
#455000
b110001 4
b101000 5
b100 .
b110001 2
b101000 3
b101000 !
b101000 0
b101000 :
b1000 8
b110 9
1%
#456000
b1 *
0&
#460000
0%
#465000
b111 8
b101 9
1#
1-
1%
#466000
b101000 "
b101000 1
1'
#470000
0%
#475000
b100111 5
b101011 4
b100111 3
b1 6
b101011 2
b11 7
b1 $
b1 ,
b1 /
b110 8
b1000 9
1%
#476000
b0 "
b0 1
0'
#480000
0%
#485000
b101 8
b111 9
1%
#486000
1&
#490000
0%
#495000
b101110 4
b101010 5
b101110 2
b101010 3
b101011 !
b101011 0
b101011 :
b1000 8
b110 9
1%
#496000
b10 *
0&
#500000
0%
#505000
b111 8
b101 9
1%
#506000
b101011 "
b101011 1
1'
#510000
0%
#515000
b101101 4
b101001 5
b101010 "
b101010 1
b101101 2
b101001 3
b101010 !
b101010 0
b101010 :
b110 8
b1000 9
1%
#516000
b0 "
b0 1
0'
#520000
0%
#525000
b101 8
b111 9
1%
#526000
1&
#530000
0%
#535000
b110000 4
b101100 5
b110000 2
b101100 3
b101101 !
b101101 0
b101101 :
b1000 8
b110 9
1%
#536000
b11 *
0&
#540000
0%
#545000
b111 8
b101 9
1%
#546000
b101101 "
b101101 1
1'
#550000
0%
#555000
b101111 4
b101011 5
b101100 "
b101100 1
b101111 2
b101011 3
b101100 !
b101100 0
b101100 :
b110 8
b1000 9
1%
#556000
b0 "
b0 1
0'
#560000
0%
#565000
b101 8
b111 9
1%
#566000
1&
#570000
0%
#575000
b110010 4
b101110 5
b110010 2
b101110 3
b101111 !
b101111 0
b101111 :
b1000 8
b110 9
1%
#576000
b100 *
0&
#580000
0%
#585000
b111 8
b101 9
1%
#586000
b101111 "
b101111 1
1'
#590000
0%
#595000
b110001 4
b101101 5
b101110 "
b101110 1
b110001 2
b101101 3
b101110 !
b101110 0
b101110 :
b110 8
b1000 9
1%
#596000
b0 "
b0 1
0'
#600000
0%
#605000
b101 8
b111 9
1%
#606000
1&
#610000
0%
#615000
b110100 4
b110000 5
b110100 2
b110000 3
b110001 !
b110001 0
b110001 :
b1000 8
b110 9
1%
#616000
b101 *
0&
#620000
0%
#625000
b111 8
b101 9
1%
#626000
b110001 "
b110001 1
1'
#630000
0%
#635000
b110011 4
b101111 5
b110000 "
b110000 1
b110011 2
b101111 3
b110000 !
b110000 0
b110000 :
b110 8
b1000 9
1%
#636000
b0 "
b0 1
0'
#640000
0%
#645000
b101 8
b111 9
1%
#646000
1&
#650000
0%
#655000
b110110 4
b110010 5
b110110 2
b110010 3
b110011 !
b110011 0
b110011 :
b1000 8
b110 9
1%
#656000
b110 *
0&
#660000
0%
#665000
b111 8
b101 9
1%
#666000
b110011 "
b110011 1
1'
#670000
0%
#675000
b110101 4
b110001 5
b110010 "
b110010 1
b110101 2
b110001 3
b110010 !
b110010 0
b110010 :
b110 8
b1000 9
1%
#676000
b0 "
b0 1
0'
#680000
0%
#685000
b101 8
b111 9
1%
#686000
1&
#690000
0%
#695000
b111000 4
b110100 5
b111000 2
b110100 3
b110101 !
b110101 0
b110101 :
b1000 8
b110 9
1%
#696000
b111 *
0&
#700000
0%
#705000
b111 8
b101 9
1%
#706000
b110101 "
b110101 1
1'
#710000
0%
#715000
b110111 4
b110011 5
b110100 "
b110100 1
b110111 2
b110011 3
b110100 !
b110100 0
b110100 :
b110 8
b1000 9
1%
#716000
b0 "
b0 1
0'
#720000
0%
#725000
b101 8
b111 9
1%
#726000
1&
#730000
0%
#735000
b111010 4
b110110 5
b111010 2
b110110 3
b110111 !
b110111 0
b110111 :
b1000 8
b110 9
1%
#736000
b1000 *
0&
#740000
0%
#745000
b111 8
b101 9
1%
#746000
b110111 "
b110111 1
1'
#750000
0%
#755000
b111001 4
b110101 5
b110110 "
b110110 1
b111001 2
b110101 3
b110110 !
b110110 0
b110110 :
b110 8
b1000 9
1%
#756000
b0 "
b0 1
0'
#760000
0%
#765000
b101 8
b111 9
1%
#766000
1&
#770000
0%
#775000
b111100 4
b111000 5
b111100 2
b111000 3
b111001 !
b111001 0
b111001 :
b1000 8
b110 9
1%
#776000
b1001 *
0&
#780000
0%
#785000
b111 8
b101 9
1%
#786000
b111001 "
b111001 1
1'
#790000
0%
#795000
b111011 4
b110111 5
b111000 "
b111000 1
b111011 2
b110111 3
b111000 !
b111000 0
b111000 :
b110 8
b1000 9
1%
#796000
b0 "
b0 1
0'
#800000
0%
#805000
b101 8
b111 9
1%
#806000
1&
#810000
0%
#815000
b111110 4
b111010 5
b111110 2
b111010 3
b111011 !
b111011 0
b111011 :
b1000 8
b110 9
1%
#816000
b0 *
0&
#820000
0%
#825000
b111 8
b101 9
1%
#826000
b111011 "
b111011 1
1'
#830000
0%
#835000
b111101 4
b111001 5
b111010 "
b111010 1
b111101 2
b111001 3
b111010 !
b111010 0
b111010 :
b110 8
b1000 9
1%
#836000
b0 "
b0 1
0'
#840000
0%
#845000
b101 8
b111 9
1%
#846000
1&
#850000
0%
#855000
b1000000 4
b111100 5
b1000000 2
b111100 3
b111101 !
b111101 0
b111101 :
b1000 8
b110 9
1%
#856000
b1 *
0&
#860000
0%
#865000
b111 8
b101 9
1%
#866000
b111101 "
b111101 1
1'
#870000
0%
#875000
b111111 4
b111011 5
b111100 "
b111100 1
b111111 2
b111011 3
b111100 !
b111100 0
b111100 :
b110 8
b1000 9
1%
#876000
b0 "
b0 1
0'
#880000
0%
#885000
b101 8
b111 9
1%
#886000
1&
#890000
0%
#895000
b1000010 4
b111110 5
b1000010 2
b111110 3
b111111 !
b111111 0
b111111 :
b1000 8
b110 9
1%
#896000
b10 *
0&
#900000
0%
#905000
b111 8
b101 9
1%
#906000
b111111 "
b111111 1
1'
#910000
0%
#915000
b1000001 4
b111101 5
b111110 "
b111110 1
b1000001 2
b111101 3
b111110 !
b111110 0
b111110 :
b110 8
b1000 9
1%
#916000
b0 "
b0 1
0'
#920000
0%
#925000
b101 8
b111 9
1%
#926000
1&
#930000
0%
#935000
b1000100 4
b1000000 5
b1000100 2
b1000000 3
b1000001 !
b1000001 0
b1000001 :
b1000 8
b110 9
1%
#936000
b11 *
0&
#940000
0%
#945000
b111 8
b101 9
1%
#946000
b1000001 "
b1000001 1
1'
#950000
0%
#955000
b1000011 4
b111111 5
b1000000 "
b1000000 1
b1000011 2
b111111 3
b1000000 !
b1000000 0
b1000000 :
b110 8
b1000 9
1%
#956000
b0 "
b0 1
0'
#960000
0%
#965000
b101 8
b111 9
1%
#966000
1&
#970000
0%
#975000
b1000110 4
b1000010 5
b1000110 2
b1000010 3
b1000011 !
b1000011 0
b1000011 :
b1000 8
b110 9
1%
#976000
b100 *
0&
#980000
0%
#985000
b111 8
b101 9
1%
#986000
b1000011 "
b1000011 1
1'
#990000
0%
#995000
b1000101 4
b1000001 5
b1000010 "
b1000010 1
b1000101 2
b1000001 3
b1000010 !
b1000010 0
b1000010 :
b110 8
b1000 9
1%
#996000
b0 "
b0 1
0'
#1000000
0%
#1005000
b101 8
b111 9
1%
#1006000
1&
#1010000
0%
#1015000
b1001000 4
b1000100 5
b1001000 2
b1000100 3
b1000101 !
b1000101 0
b1000101 :
b1000 8
b110 9
1%
#1016000
b101 *
0&
#1020000
0%
#1025000
b111 8
b101 9
1%
#1026000
b1000101 "
b1000101 1
1'
#1030000
0%
#1035000
b1000111 4
b1000011 5
b1000100 "
b1000100 1
b1000111 2
b1000011 3
b1000100 !
b1000100 0
b1000100 :
b110 8
b1000 9
1%
#1036000
b0 "
b0 1
0'
#1040000
0%
#1045000
b101 8
b111 9
1%
#1046000
1&
#1050000
0%
#1055000
b1001010 4
b1000110 5
b1001010 2
b1000110 3
b1000111 !
b1000111 0
b1000111 :
b1000 8
b110 9
1%
#1056000
b110 *
0&
#1060000
0%
#1065000
b111 8
b101 9
1%
#1066000
b1000111 "
b1000111 1
1'
#1070000
0%
#1075000
b1001001 4
b1000101 5
b1000110 "
b1000110 1
b1001001 2
b1000101 3
b1000110 !
b1000110 0
b1000110 :
b110 8
b1000 9
1%
#1076000
b0 "
b0 1
0'
#1080000
0%
#1085000
b101 8
b111 9
1%
#1086000
1&
#1090000
0%
#1095000
b1001100 4
b1001000 5
b1001100 2
b1001000 3
b1001001 !
b1001001 0
b1001001 :
b1000 8
b110 9
1%
#1096000
b111 *
0&
#1100000
0%
#1105000
b111 8
b101 9
1%
#1106000
b1001001 "
b1001001 1
1'
#1110000
0%
#1115000
b1001011 4
b1000111 5
b1001000 "
b1001000 1
b1001011 2
b1000111 3
b1001000 !
b1001000 0
b1001000 :
b110 8
b1000 9
1%
#1116000
b0 "
b0 1
0'
#1120000
0%
#1125000
b101 8
b111 9
1%
#1126000
1&
#1130000
0%
#1135000
b1001110 4
b1001010 5
b1001110 2
b1001010 3
b1001011 !
b1001011 0
b1001011 :
b1000 8
b110 9
1%
#1136000
b1000 *
0&
#1140000
0%
#1145000
b111 8
b101 9
1%
#1146000
b1001011 "
b1001011 1
1'
#1150000
0%
#1155000
b1001101 4
b1001001 5
b1001010 "
b1001010 1
b1001101 2
b1001001 3
b1001010 !
b1001010 0
b1001010 :
b110 8
b1000 9
1%
#1156000
b0 "
b0 1
0'
#1160000
0%
#1165000
b101 8
b111 9
1%
#1166000
1&
#1170000
0%
#1175000
b1010000 4
b1001100 5
b1010000 2
b1001100 3
b1001101 !
b1001101 0
b1001101 :
b1000 8
b110 9
1%
#1176000
b1001 *
0&
#1180000
0%
#1185000
b111 8
b101 9
1%
#1186000
b1001101 "
b1001101 1
1'
#1190000
0%
#1195000
b1001111 4
b1001011 5
b1001100 "
b1001100 1
b1001111 2
b1001011 3
b1001100 !
b1001100 0
b1001100 :
b110 8
b1000 9
1%
#1196000
b0 "
b0 1
0'
#1200000
0%
#1205000
b101 8
b111 9
1%
#1206000
1&
#1210000
0%
#1215000
b1010010 4
b1001110 5
b1010010 2
b1001110 3
b1001111 !
b1001111 0
b1001111 :
b1000 8
b110 9
1%
#1216000
b1010 *
0&
#1220000
0%
#1225000
b111 8
b101 9
1%
#1226000
b1001111 "
b1001111 1
1'
#1230000
0%
#1235000
b1010001 4
b1001101 5
b1001110 "
b1001110 1
b1010001 2
b1001101 3
b1001110 !
b1001110 0
b1001110 :
b110 8
b1000 9
1%
#1236000
b0 "
b0 1
0'
#1240000
0%
#1245000
b101 8
b111 9
1%
#1246000
1&
#1250000
0%
#1255000
b1010100 4
b1010000 5
b1010100 2
b1010000 3
b1010001 !
b1010001 0
b1010001 :
b1000 8
b110 9
1%
#1256000
b1011 *
0&
#1260000
0%
#1265000
b111 8
b101 9
1%
#1266000
b1010001 "
b1010001 1
1'
#1270000
0%
#1275000
b1010011 4
b1001111 5
b1010000 "
b1010000 1
b1010011 2
b1001111 3
b1010000 !
b1010000 0
b1010000 :
b110 8
b1000 9
1%
#1276000
b0 "
b0 1
0'
#1280000
0%
#1285000
b101 8
b111 9
1%
#1286000
1&
#1290000
0%
#1295000
b1010110 4
b1010010 5
b1010110 2
b1010010 3
b1010011 !
b1010011 0
b1010011 :
b1000 8
b110 9
1%
#1296000
b1100 *
0&
#1300000
0%
#1305000
b111 8
b101 9
1%
#1306000
b1010011 "
b1010011 1
1'
#1310000
0%
#1315000
b1010101 4
b1010001 5
b1010010 "
b1010010 1
b1010101 2
b1010001 3
b1010010 !
b1010010 0
b1010010 :
b110 8
b1000 9
1%
#1316000
b0 "
b0 1
0'
#1320000
0%
#1325000
b101 8
b111 9
1%
#1326000
1&
#1330000
0%
#1335000
b1011000 4
b1010100 5
b1011000 2
b1010100 3
b1010101 !
b1010101 0
b1010101 :
b1000 8
b110 9
1%
#1336000
b1101 *
0&
#1340000
0%
#1345000
b111 8
b101 9
1%
